{
  "prereg": "preregs/E43_chieff_dynamical_channel_prereg.md",
  "n_events": 75,
  "n_P_neg_gt_0.90": 0,
  "events_P_neg_gt_0.90": [],
  "n_P_neg_gt_0.975": 0,
  "events_P_neg_gt_0.975": [],
  "n_ci95_all_neg": 0,
  "events_ci95_all_neg": [],
  "median_neg_fraction_E42style": 0.347,
  "D1_pass": false,
  "D2_pass": false,
  "per_event": [
    {
      "event": "GW191109_010717",
      "n": 32415,
      "median": -0.293,
      "p_neg": 0.9,
      "q5": -0.602,
      "q95": 0.124,
      "q2p5": -0.653,
      "q97p5": 0.237,
      "ci90_all_neg": false,
      "ci95_all_neg": false
    },
    {
      "event": "GW200115_042309",
      "n": 31903,
      "median": -0.153,
      "p_neg": 0.818,
      "q5": -0.568,
      "q95": 0.084,
      "q2p5": -0.587,
      "q97p5": 0.14,
      "ci90_all_neg": false,
      "ci95_all_neg": false
    },
    {
      "event": "GW200209_085452",
      "n": 9015,
      "median": -0.117,
      "p_neg": 0.777,
      "q5": -0.419,
      "q95": 0.128,
      "q2p5": -0.482,
      "q97p5": 0.176,
      "ci90_all_neg": false,
      "ci95_all_neg": false
    },
    {
      "event": "GW200225_060421",
      "n": 15593,
      "median": -0.116,
      "p_neg": 0.846,
      "q5": -0.395,
      "q95": 0.056,
      "q2p5": -0.438,
      "q97p5": 0.084,
      "ci90_all_neg": false,
      "ci95_all_neg": false
    },
    {
      "event": "GW190421_213856",
      "n": 30870,
      "median": -0.095,
      "p_neg": 0.765,
      "q5": -0.37,
      "q95": 0.117,
      "q2p5": -0.432,
      "q97p5": 0.159,
      "ci90_all_neg": false,
      "ci95_all_neg": false
    },
    {
      "event": "GW190701_203306",
      "n": 22577,
      "median": -0.082,
      "p_neg": 0.716,
      "q5": -0.39,
      "q95": 0.149,
      "q2p5": -0.451,
      "q97p5": 0.195,
      "ci90_all_neg": false,
      "ci95_all_neg": false
    },
    {
      "event": "GW200219_094415",
      "n": 9991,
      "median": -0.08,
      "p_neg": 0.712,
      "q5": -0.37,
      "q95": 0.151,
      "q2p5": -0.429,
      "q97p5": 0.197,
      "ci90_all_neg": false,
      "ci95_all_neg": false
    },
    {
      "event": "GW190514_065416",
      "n": 6960,
      "median": -0.079,
      "p_neg": 0.676,
      "q5": -0.432,
      "q95": 0.21,
      "q2p5": -0.499,
      "q97p5": 0.268,
      "ci90_all_neg": false,
      "ci95_all_neg": false
    },
    {
      "event": "GW190917_114630",
      "n": 12260,
      "median": -0.075,
      "p_neg": 0.717,
      "q5": -0.505,
      "q95": 0.134,
      "q2p5": -0.553,
      "q97p5": 0.223,
      "ci90_all_neg": false,
      "ci95_all_neg": false
    },
    {
      "event": "GW200220_124850",
      "n": 4861,
      "median": -0.075,
      "p_neg": 0.68,
      "q5": -0.403,
      "q95": 0.196,
      "q2p5": -0.475,
      "q97p5": 0.262,
      "ci90_all_neg": false,
      "ci95_all_neg": false
    },
    {
      "event": "GW200208_130117",
      "n": 14981,
      "median": -0.068,
      "p_neg": 0.699,
      "q5": -0.335,
      "q95": 0.148,
      "q2p5": -0.389,
      "q97p5": 0.191,
      "ci90_all_neg": false,
      "ci95_all_neg": false
    },
    {
      "event": "GW191230_180458",
      "n": 7026,
      "median": -0.049,
      "p_neg": 0.625,
      "q5": -0.357,
      "q95": 0.213,
      "q2p5": -0.436,
      "q97p5": 0.263,
      "ci90_all_neg": false,
      "ci95_all_neg": false
    },
    {
      "event": "GW190503_185404",
      "n": 24159,
      "median": -0.045,
      "p_neg": 0.625,
      "q5": -0.35,
      "q95": 0.18,
      "q2p5": -0.416,
      "q97p5": 0.223,
      "ci90_all_neg": false,
      "ci95_all_neg": false
    },
    {
      "event": "GW191215_223052",
      "n": 8884,
      "median": -0.041,
      "p_neg": 0.653,
      "q5": -0.249,
      "q95": 0.127,
      "q2p5": -0.296,
      "q97p5": 0.162,
      "ci90_all_neg": false,
      "ci95_all_neg": false
    },
    {
      "event": "GW191222_033537",
      "n": 8528,
      "median": -0.041,
      "p_neg": 0.63,
      "q5": -0.289,
      "q95": 0.156,
      "q2p5": -0.347,
      "q97p5": 0.197,
      "ci90_all_neg": false,
      "ci95_all_neg": false
    },
    {
      "event": "GW190725_174728",
      "n": 79172,
      "median": -0.039,
      "p_neg": 0.611,
      "q5": -0.205,
      "q95": 0.318,
      "q2p5": -0.258,
      "q97p5": 0.496,
      "ci90_all_neg": false,
      "ci95_all_neg": false
    },
    {
      "event": "GW190707_093326",
      "n": 19897,
      "median": -0.037,
      "p_neg": 0.733,
      "q5": -0.126,
      "q95": 0.062,
      "q2p5": -0.139,
      "q97p5": 0.086,
      "ci90_all_neg": false,
      "ci95_all_neg": false
    },
    {
      "event": "GW190929_012149",
      "n": 30673,
      "median": -0.032,
      "p_neg": 0.599,
      "q5": -0.311,
      "q95": 0.201,
      "q2p5": -0.374,
      "q97p5": 0.253,
      "ci90_all_neg": false,
      "ci95_all_neg": false
    },
    {
      "event": "GW190408_181802",
      "n": 10527,
      "median": -0.026,
      "p_neg": 0.63,
      "q5": -0.196,
      "q95": 0.109,
      "q2p5": -0.243,
      "q97p5": 0.134,
      "ci90_all_neg": false,
      "ci95_all_neg": false
    },
    {
      "event": "GW190915_235702",
      "n": 21302,
      "median": -0.025,
      "p_neg": 0.587,
      "q5": -0.262,
      "q95": 0.161,
      "q2p5": -0.31,
      "q97p5": 0.198,
      "ci90_all_neg": false,
      "ci95_all_neg": false
    },
    {
      "event": "GW190926_050336",
      "n": 20412,
      "median": -0.02,
      "p_neg": 0.558,
      "q5": -0.351,
      "q95": 0.227,
      "q2p5": -0.434,
      "q97p5": 0.28,
      "ci90_all_neg": false,
      "ci95_all_neg": false
    },
    {
      "event": "GW200311_115853",
      "n": 20276,
      "median": -0.019,
      "p_neg": 0.579,
      "q5": -0.221,
      "q95": 0.136,
      "q2p5": -0.262,
      "q97p5": 0.168,
      "ci90_all_neg": false,
      "ci95_all_neg": false
    },
    {
      "event": "GW191105_143521",
      "n": 16861,
      "median": -0.018,
      "p_neg": 0.627,
      "q5": -0.111,
      "q95": 0.113,
      "q2p5": -0.133,
      "q97p5": 0.161,
      "ci90_all_neg": false,
      "ci95_all_neg": false
    },
    {
      "event": "GW190803_022701",
      "n": 20702,
      "median": -0.015,
      "p_neg": 0.544,
      "q5": -0.29,
      "q95": 0.211,
      "q2p5": -0.352,
      "q97p5": 0.253,
      "ci90_all_neg": false,
      "ci95_all_neg": false
    },
    {
      "event": "GW190413_134308",
      "n": 23732,
      "median": -0.007,
      "p_neg": 0.517,
      "q5": -0.388,
      "q95": 0.274,
      "q2p5": -0.468,
      "q97p5": 0.326,
      "ci90_all_neg": false,
      "ci95_all_neg": false
    },
    {
      "event": "GW190910_112807",
      "n": 17857,
      "median": -0.003,
      "p_neg": 0.512,
      "q5": -0.198,
      "q95": 0.171,
      "q2p5": -0.24,
      "q97p5": 0.207,
      "ci90_all_neg": false,
      "ci95_all_neg": false
    },
    {
      "event": "GW191219_163120",
      "n": 27115,
      "median": -0.0,
      "p_neg": 0.502,
      "q5": -0.089,
      "q95": 0.07,
      "q2p5": -0.119,
      "q97p5": 0.087,
      "ci90_all_neg": false,
      "ci95_all_neg": false
    },
    {
      "event": "GW191113_071753",
      "n": 20354,
      "median": 0.003,
      "p_neg": 0.488,
      "q5": -0.289,
      "q95": 0.374,
      "q2p5": -0.365,
      "q97p5": 0.499,
      "ci90_all_neg": false,
      "ci95_all_neg": false
    },
    {
      "event": "GW190814",
      "n": 78224,
      "median": 0.004,
      "p_neg": 0.454,
      "q5": -0.07,
      "q95": 0.075,
      "q2p5": -0.093,
      "q97p5": 0.092,
      "ci90_all_neg": false,
      "ci95_all_neg": false
    },
    {
      "event": "GW200302_015811",
      "n": 18183,
      "median": 0.014,
      "p_neg": 0.451,
      "q5": -0.243,
      "q95": 0.263,
      "q2p5": -0.315,
      "q97p5": 0.314,
      "ci90_all_neg": false,
      "ci95_all_neg": false
    },
    {
      "event": "GW200210_092254",
      "n": 28099,
      "median": 0.02,
      "p_neg": 0.421,
      "q5": -0.194,
      "q95": 0.243,
      "q2p5": -0.252,
      "q97p5": 0.279,
      "ci90_all_neg": false,
      "ci95_all_neg": false
    },
    {
      "event": "GW190512_180714",
      "n": 19213,
      "median": 0.024,
      "p_neg": 0.364,
      "q5": -0.112,
      "q95": 0.152,
      "q2p5": -0.147,
      "q97p5": 0.183,
      "ci90_all_neg": false,
      "ci95_all_neg": false
    },
    {
      "event": "GW190924_021846",
      "n": 34848,
      "median": 0.025,
      "p_neg": 0.351,
      "q5": -0.057,
      "q95": 0.226,
      "q2p5": -0.068,
      "q97p5": 0.304,
      "ci90_all_neg": false,
      "ci95_all_neg": false
    },
    {
      "event": "GW200202_154313",
      "n": 43480,
      "median": 0.039,
      "p_neg": 0.143,
      "q5": -0.018,
      "q95": 0.165,
      "q2p5": -0.029,
      "q97p5": 0.207,
      "ci90_all_neg": false,
      "ci95_all_neg": false
    },
    {
      "event": "GW191204_110529",
      "n": 13750,
      "median": 0.052,
      "p_neg": 0.349,
      "q5": -0.211,
      "q95": 0.299,
      "q2p5": -0.274,
      "q97p5": 0.354,
      "ci90_all_neg": false,
      "ci95_all_neg": false
    },
    {
      "event": "GW190708_232457",
      "n": 17719,
      "median": 0.054,
      "p_neg": 0.2,
      "q5": -0.046,
      "q95": 0.159,
      "q2p5": -0.065,
      "q97p5": 0.178,
      "ci90_all_neg": false,
      "ci95_all_neg": false
    },
    {
      "event": "GW190828_065509",
      "n": 71641,
      "median": 0.054,
      "p_neg": 0.286,
      "q5": -0.116,
      "q95": 0.214,
      "q2p5": -0.156,
      "q97p5": 0.247,
      "ci90_all_neg": false,
      "ci95_all_neg": false
    },
    {
      "event": "GW200220_061928",
      "n": 3032,
      "median": 0.06,
      "p_neg": 0.391,
      "q5": -0.325,
      "q95": 0.46,
      "q2p5": -0.405,
      "q97p5": 0.531,
      "ci90_all_neg": false,
      "ci95_all_neg": false
    },
    {
      "event": "GW191129_134029",
      "n": 24169,
      "median": 0.064,
      "p_neg": 0.093,
      "q5": -0.012,
      "q95": 0.226,
      "q2p5": -0.022,
      "q97p5": 0.261,
      "ci90_all_neg": false,
      "ci95_all_neg": false
    },
    {
      "event": "GW190425",
      "n": 20000,
      "median": 0.065,
      "p_neg": 0.002,
      "q5": 0.012,
      "q95": 0.134,
      "q2p5": 0.008,
      "q97p5": 0.15,
      "ci90_all_neg": false,
      "ci95_all_neg": false
    },
    {
      "event": "GW200112_155838",
      "n": 4323,
      "median": 0.065,
      "p_neg": 0.231,
      "q5": -0.086,
      "q95": 0.214,
      "q2p5": -0.116,
      "q97p5": 0.241,
      "ci90_all_neg": false,
      "ci95_all_neg": false
    },
    {
      "event": "GW190731_140936",
      "n": 5529,
      "median": 0.074,
      "p_neg": 0.303,
      "q5": -0.173,
      "q95": 0.351,
      "q2p5": -0.228,
      "q97p5": 0.403,
      "ci90_all_neg": false,
      "ci95_all_neg": false
    },
    {
      "event": "GW190925_232845",
      "n": 29450,
      "median": 0.086,
      "p_neg": 0.164,
      "q5": -0.062,
      "q95": 0.249,
      "q2p5": -0.095,
      "q97p5": 0.288,
      "ci90_all_neg": false,
      "ci95_all_neg": false
    },
    {
      "event": "GW190727_060333",
      "n": 11530,
      "median": 0.094,
      "p_neg": 0.263,
      "q5": -0.172,
      "q95": 0.344,
      "q2p5": -0.232,
      "q97p5": 0.392,
      "ci90_all_neg": false,
      "ci95_all_neg": false
    },
    {
      "event": "GW190521_074359",
      "n": 8111,
      "median": 0.096,
      "p_neg": 0.109,
      "q5": -0.031,
      "q95": 0.224,
      "q2p5": -0.053,
      "q97p5": 0.243,
      "ci90_all_neg": false,
      "ci95_all_neg": false
    },
    {
      "event": "GW190527_092055",
      "n": 13819,
      "median": 0.096,
      "p_neg": 0.213,
      "q5": -0.124,
      "q95": 0.32,
      "q2p5": -0.201,
      "q97p5": 0.371,
      "ci90_all_neg": false,
      "ci95_all_neg": false
    },
    {
      "event": "GW200216_220804",
      "n": 6038,
      "median": 0.096,
      "p_neg": 0.312,
      "q5": -0.262,
      "q95": 0.438,
      "q2p5": -0.339,
      "q97p5": 0.497,
      "ci90_all_neg": false,
      "ci95_all_neg": false
    },
    {
      "event": "GW200224_222234",
      "n": 11459,
      "median": 0.099,
      "p_neg": 0.143,
      "q5": -0.053,
      "q95": 0.246,
      "q2p5": -0.085,
      "q97p5": 0.275,
      "ci90_all_neg": false,
      "ci95_all_neg": false
    },
    {
      "event": "GW190630_185205",
      "n": 16770,
      "median": 0.101,
      "p_neg": 0.104,
      "q5": -0.03,
      "q95": 0.244,
      "q2p5": -0.06,
      "q97p5": 0.273,
      "ci90_all_neg": false,
      "ci95_all_neg": false
    },
    {
      "event": "GW191216_213338",
      "n": 13919,
      "median": 0.111,
      "p_neg": 0.001,
      "q5": 0.049,
      "q95": 0.245,
      "q2p5": 0.039,
      "q97p5": 0.311,
      "ci90_all_neg": false,
      "ci95_all_neg": false
    },
    {
      "event": "GW200129_065458",
      "n": 1993,
      "median": 0.112,
      "p_neg": 0.106,
      "q5": -0.045,
      "q95": 0.226,
      "q2p5": -0.085,
      "q97p5": 0.25,
      "ci90_all_neg": false,
      "ci95_all_neg": false
    },
    {
      "event": "GW190602_175927",
      "n": 34485,
      "median": 0.116,
      "p_neg": 0.23,
      "q5": -0.163,
      "q95": 0.366,
      "q2p5": -0.238,
      "q97p5": 0.408,
      "ci90_all_neg": false,
      "ci95_all_neg": false
    },
    {
      "event": "GW200128_022011",
      "n": 6638,
      "median": 0.121,
      "p_neg": 0.208,
      "q5": -0.127,
      "q95": 0.359,
      "q2p5": -0.173,
      "q97p5": 0.407,
      "ci90_all_neg": false,
      "ci95_all_neg": false
    },
    {
      "event": "GW200316_215756",
      "n": 129267,
      "median": 0.126,
      "p_neg": 0.017,
      "q5": 0.024,
      "q95": 0.394,
      "q2p5": 0.008,
      "q97p5": 0.445,
      "ci90_all_neg": false,
      "ci95_all_neg": false
    },
    {
      "event": "GW190728_064510",
      "n": 11756,
      "median": 0.133,
      "p_neg": 0.001,
      "q5": 0.059,
      "q95": 0.328,
      "q2p5": 0.048,
      "q97p5": 0.391,
      "ci90_all_neg": false,
      "ci95_all_neg": false
    },
    {
      "event": "GW190828_063405",
      "n": 42966,
      "median": 0.154,
      "p_neg": 0.052,
      "q5": -0.002,
      "q95": 0.306,
      "q2p5": -0.032,
      "q97p5": 0.334,
      "ci90_all_neg": false,
      "ci95_all_neg": false
    },
    {
      "event": "GW200308_173609",
      "n": 1073,
      "median": 0.158,
      "p_neg": 0.318,
      "q5": -0.332,
      "q95": 0.739,
      "q2p5": -0.421,
      "q97p5": 0.795,
      "ci90_all_neg": false,
      "ci95_all_neg": false
    },
    {
      "event": "GW191204_171526",
      "n": 17844,
      "median": 0.159,
      "p_neg": 0.0,
      "q5": 0.11,
      "q95": 0.24,
      "q2p5": 0.102,
      "q97p5": 0.259,
      "ci90_all_neg": false,
      "ci95_all_neg": false
    },
    {
      "event": "GW190513_205428",
      "n": 13281,
      "median": 0.163,
      "p_neg": 0.121,
      "q5": -0.055,
      "q95": 0.451,
      "q2p5": -0.094,
      "q97p5": 0.504,
      "ci90_all_neg": false,
      "ci95_all_neg": false
    },
    {
      "event": "GW191127_050227",
      "n": 7811,
      "median": 0.179,
      "p_neg": 0.206,
      "q5": -0.18,
      "q95": 0.517,
      "q2p5": -0.256,
      "q97p5": 0.574,
      "ci90_all_neg": false,
      "ci95_all_neg": false
    },
    {
      "event": "GW190720_000836",
      "n": 26439,
      "median": 0.193,
      "p_neg": 0.001,
      "q5": 0.081,
      "q95": 0.33,
      "q2p5": 0.063,
      "q97p5": 0.357,
      "ci90_all_neg": false,
      "ci95_all_neg": false
    },
    {
      "event": "GW190930_133541",
      "n": 34482,
      "median": 0.193,
      "p_neg": 0.027,
      "q5": 0.029,
      "q95": 0.414,
      "q2p5": -0.003,
      "q97p5": 0.473,
      "ci90_all_neg": false,
      "ci95_all_neg": false
    },
    {
      "event": "GW190916_200658",
      "n": 7011,
      "median": 0.204,
      "p_neg": 0.149,
      "q5": -0.106,
      "q95": 0.534,
      "q2p5": -0.167,
      "q97p5": 0.582,
      "ci90_all_neg": false,
      "ci95_all_neg": false
    },
    {
      "event": "GW191126_115259",
      "n": 23523,
      "median": 0.207,
      "p_neg": 0.002,
      "q5": 0.094,
      "q95": 0.353,
      "q2p5": 0.074,
      "q97p5": 0.391,
      "ci90_all_neg": false,
      "ci95_all_neg": false
    },
    {
      "event": "GW191103_012549",
      "n": 9859,
      "median": 0.211,
      "p_neg": 0.001,
      "q5": 0.111,
      "q95": 0.371,
      "q2p5": 0.096,
      "q97p5": 0.418,
      "ci90_all_neg": false,
      "ci95_all_neg": false
    },
    {
      "event": "GW190412",
      "n": 7886,
      "median": 0.214,
      "p_neg": 0.001,
      "q5": 0.087,
      "q95": 0.338,
      "q2p5": 0.073,
      "q97p5": 0.357,
      "ci90_all_neg": false,
      "ci95_all_neg": false
    },
    {
      "event": "GW190426_190642",
      "n": 16781,
      "median": 0.226,
      "p_neg": 0.189,
      "q5": -0.185,
      "q95": 0.647,
      "q2p5": -0.281,
      "q97p5": 0.706,
      "ci90_all_neg": false,
      "ci95_all_neg": false
    },
    {
      "event": "GW190719_215514",
      "n": 20337,
      "median": 0.251,
      "p_neg": 0.102,
      "q5": -0.071,
      "q95": 0.577,
      "q2p5": -0.133,
      "q97p5": 0.633,
      "ci90_all_neg": false,
      "ci95_all_neg": false
    },
    {
      "event": "GW190706_222641",
      "n": 6316,
      "median": 0.282,
      "p_neg": 0.065,
      "q5": -0.03,
      "q95": 0.535,
      "q2p5": -0.099,
      "q97p5": 0.578,
      "ci90_all_neg": false,
      "ci95_all_neg": false
    },
    {
      "event": "GW200306_093714",
      "n": 14034,
      "median": 0.316,
      "p_neg": 0.149,
      "q5": -0.148,
      "q95": 0.599,
      "q2p5": -0.24,
      "q97p5": 0.648,
      "ci90_all_neg": false,
      "ci95_all_neg": false
    },
    {
      "event": "GW190519_153544",
      "n": 11339,
      "median": 0.331,
      "p_neg": 0.016,
      "q5": 0.09,
      "q95": 0.527,
      "q2p5": 0.039,
      "q97p5": 0.563,
      "ci90_all_neg": false,
      "ci95_all_neg": false
    },
    {
      "event": "GW190620_030421",
      "n": 8895,
      "median": 0.34,
      "p_neg": 0.033,
      "q5": 0.054,
      "q95": 0.559,
      "q2p5": -0.035,
      "q97p5": 0.596,
      "ci90_all_neg": false,
      "ci95_all_neg": false
    },
    {
      "event": "GW190805_211137",
      "n": 6196,
      "median": 0.368,
      "p_neg": 0.06,
      "q5": -0.025,
      "q95": 0.66,
      "q2p5": -0.109,
      "q97p5": 0.709,
      "ci90_all_neg": false,
      "ci95_all_neg": false
    },
    {
      "event": "GW190517_055101",
      "n": 15688,
      "median": 0.491,
      "p_neg": 0.007,
      "q5": 0.213,
      "q95": 0.699,
      "q2p5": 0.148,
      "q97p5": 0.736,
      "ci90_all_neg": false,
      "ci95_all_neg": false
    },
    {
      "event": "GW190403_051519",
      "n": 3164,
      "median": 0.679,
      "p_neg": 0.012,
      "q5": 0.253,
      "q95": 0.836,
      "q2p5": 0.115,
      "q97p5": 0.866,
      "ci90_all_neg": false,
      "ci95_all_neg": false
    }
  ]
}