{
 "battery": "E96 curve thickness mechanism",
 "seed": 96,
 "provenance": {
  "cache": "results/e94_posterior_cache.npz",
  "manifest": "results/e94_posterior_cache_manifest.json",
  "cache_manifest": {
   "n_events": 266,
   "n_group_rows": 972,
   "catalogs": {
    "GWTC-3": {
     "files": 76,
     "events_cached": 76,
     "group_rows": 226,
     "seconds": 90.1
    },
    "O4a": {
     "files": 86,
     "events_cached": 86,
     "group_rows": 369,
     "seconds": 7.4
    },
    "O4b": {
     "files": 105,
     "events_cached": 104,
     "group_rows": 377,
     "seconds": 6.8
    }
   },
   "n_samp": null,
   "seed": 94,
   "skipped": {},
   "subsampling": "NONE -- every usable sample cached; cache-backed numbers are full-sample numbers",
   "rows_stored_exactly": 972,
   "samples_stored": 23145241
  },
  "hdf5_accessed": false
 },
 "estimator": {
  "n_bins": 6,
  "min_per_bin": 20,
  "min_good_bins": 4,
  "width_statistic": "std of perpendicular offset within equal-count q bins",
  "smoothing": "none; linear interpolation between bin centres, clamped",
  "normal_finite_difference_dq": 0.0001,
  "n_model_samples": 8000
 },
 "estimator_controls": {
  "constant": [
   {
    "mc": 25.0,
    "true_w": 1.0,
    "spearman_w_q": -0.3142857142857143,
    "w_first": 0.9954608623091563,
    "w_last": 0.995330833999266
   },
   {
    "mc": 25.0,
    "true_w": 3.0,
    "spearman_w_q": -0.7142857142857143,
    "w_first": 3.0186048950248923,
    "w_last": 2.980195051975726
   },
   {
    "mc": 10.0,
    "true_w": 0.5,
    "spearman_w_q": -0.3714285714285715,
    "w_first": 0.5018006725130381,
    "w_last": 0.49845196367483885
   },
   {
    "mc": 60.0,
    "true_w": 2.0,
    "spearman_w_q": 0.7714285714285715,
    "w_first": 1.9970411148736094,
    "w_last": 2.0012224924817774
   }
  ],
  "growing": [
   {
    "mc": 25.0,
    "slope": 0.5,
    "spearman_w_q": 1.0,
    "w_first": 1.03465694183675,
    "w_last": 1.4540373100946453
   },
   {
    "mc": 25.0,
    "slope": 1.5,
    "spearman_w_q": 1.0,
    "w_first": 1.1424837372212453,
    "w_last": 2.3769398099936194
   }
  ]
 },
 "in_sample": {
  "n": 80,
  "median_signed_pure": -0.7487191711220902,
  "median_signed_thick": -0.6640119850225403,
  "median_abs_pure": 1.0659513352967878,
  "median_abs_thick": 0.8977357531092736,
  "frac_improved": 0.6625,
  "wilcoxon_p": 0.0004230496298448532,
  "median_spearman_w_q": 1.0,
  "frac_spearman_eq_1": 0.7125,
  "median_relative_thickness": 0.33702576506359305,
  "caveat": "IN-SAMPLE: w(q) is learned from the same posterior it then helps reconstruct, and adds flexibility. Improvement here is not evidence of mechanism."
 },
 "cross_family": {
  "AtoB": {
   "n": 64,
   "pure_curve": 1.201812530879721,
   "measured": 0.9078380754791908,
   "measured_beats_pure_frac": 0.703125,
   "measured_vs_pure_wilcoxon_p": 0.00028937817953923864,
   "constant": 0.9042313776580073,
   "constant_beats_pure_frac": 0.671875,
   "constant_vs_pure_wilcoxon_p": 0.009651695666252385,
   "linear": 1.0087770565636447,
   "linear_beats_pure_frac": 0.671875,
   "linear_vs_pure_wilcoxon_p": 0.0037832648700789305,
   "quadratic": 1.0531122332208582,
   "quadratic_beats_pure_frac": 0.65625,
   "quadratic_vs_pure_wilcoxon_p": 0.006897520979453376
  },
  "BtoA": {
   "n": 64,
   "pure_curve": 0.9194465530996894,
   "measured": 0.719023319624597,
   "measured_beats_pure_frac": 0.609375,
   "measured_vs_pure_wilcoxon_p": 0.007623288988028127,
   "constant": 0.772074892335155,
   "constant_beats_pure_frac": 0.625,
   "constant_vs_pure_wilcoxon_p": 0.04701235328958607,
   "linear": 0.7897366767949592,
   "linear_beats_pure_frac": 0.625,
   "linear_vs_pure_wilcoxon_p": 0.026858782195631373,
   "quadratic": 0.8862152819408919,
   "quadratic_beats_pure_frac": 0.609375,
   "quadratic_vs_pure_wilcoxon_p": 0.05410420475195937
  }
 },
 "verdict": {
  "finite_thickness": "SUPPORTED OUT-OF-SAMPLE",
  "arc_variation": "NOT ESTABLISHED",
  "statement": "FINITE thickness improves cross-family prediction in both directions, so the zero-thickness idealization is genuinely part of the residual. But the ARC-VARYING part is NOT established: a constant or simple linear taper does as well as or better than the measured profile. Do not claim the measured taper is the mechanism, and do not quote a fraction of the residual explained."
 },
 "events_in_sample": [
  {
   "catalog": "GWTC-3",
   "event": "GW190412",
   "axr": 9.535323055584811,
   "signed_pure": -0.8781682573778369,
   "signed_thick": -0.8527902244894676,
   "abs_pure": 0.8781682573778369,
   "abs_thick": 0.8527902244894676,
   "spearman_w_q": 1.0,
   "w_median_rel": 0.1622277643228807,
   "n_bins": 6
  },
  {
   "catalog": "GWTC-3",
   "event": "GW190425",
   "axr": 11.53852763980315,
   "signed_pure": -0.6710782451794444,
   "signed_thick": -0.7770744067589703,
   "abs_pure": 0.6710782451794444,
   "abs_thick": 0.7770744067589703,
   "spearman_w_q": 1.0,
   "w_median_rel": 0.12287528548380884,
   "n_bins": 6
  },
  {
   "catalog": "GWTC-3",
   "event": "GW190512_180714",
   "axr": 3.63475024908264,
   "signed_pure": -1.2048770361016352,
   "signed_thick": -1.295630070667812,
   "abs_pure": 1.2048770361016352,
   "abs_thick": 1.295630070667812,
   "spearman_w_q": 1.0,
   "w_median_rel": 0.48055429992168547,
   "n_bins": 6
  },
  {
   "catalog": "GWTC-3",
   "event": "GW190707_093326",
   "axr": 3.247158655324338,
   "signed_pure": -0.9961560559449936,
   "signed_thick": -2.8102365945085808,
   "abs_pure": 0.9961560559449936,
   "abs_thick": 2.8102365945085808,
   "spearman_w_q": 0.6,
   "w_median_rel": 0.4162869182348172,
   "n_bins": 6
  },
  {
   "catalog": "GWTC-3",
   "event": "GW190708_232457",
   "axr": 4.250074977723277,
   "signed_pure": -0.5128778651778418,
   "signed_thick": -0.4134834993745642,
   "abs_pure": 0.5128778651778418,
   "abs_thick": 0.4134834993745642,
   "spearman_w_q": 1.0,
   "w_median_rel": 0.38371141142266496,
   "n_bins": 6
  },
  {
   "catalog": "GWTC-3",
   "event": "GW190720_000836",
   "axr": 5.25139917494301,
   "signed_pure": -1.0304650038031014,
   "signed_thick": -0.7015868910503968,
   "abs_pure": 1.0304650038031014,
   "abs_thick": 0.7015868910503968,
   "spearman_w_q": 0.8285714285714287,
   "w_median_rel": 0.26970831874176676,
   "n_bins": 6
  },
  {
   "catalog": "GWTC-3",
   "event": "GW190725_174728",
   "axr": 6.81906550624828,
   "signed_pure": -0.6895422987673498,
   "signed_thick": -0.6532574385883549,
   "abs_pure": 0.6895422987673498,
   "abs_thick": 0.6532574385883549,
   "spearman_w_q": 1.0,
   "w_median_rel": 0.11641360181062459,
   "n_bins": 6
  },
  {
   "catalog": "GWTC-3",
   "event": "GW190728_064510",
   "axr": 6.0069814827025585,
   "signed_pure": -1.0377203279294065,
   "signed_thick": -1.008166622742209,
   "abs_pure": 1.0377203279294065,
   "abs_thick": 1.008166622742209,
   "spearman_w_q": 1.0,
   "w_median_rel": 0.1378006129858375,
   "n_bins": 6
  },
  {
   "catalog": "GWTC-3",
   "event": "GW190814",
   "axr": 36.730156711077434,
   "signed_pure": -0.3485313320625494,
   "signed_thick": -0.3065141394497459,
   "abs_pure": 0.3485313320625494,
   "abs_thick": 0.3065141394497459,
   "spearman_w_q": 1.0,
   "w_median_rel": 0.03198894246687046,
   "n_bins": 6
  },
  {
   "catalog": "GWTC-3",
   "event": "GW190828_065509",
   "axr": 4.008723915978267,
   "signed_pure": -1.140188838281631,
   "signed_thick": -0.3764174475390689,
   "abs_pure": 1.140188838281631,
   "abs_thick": 0.3764174475390689,
   "spearman_w_q": 1.0,
   "w_median_rel": 0.3550609561766097,
   "n_bins": 6
  },
  {
   "catalog": "GWTC-3",
   "event": "GW190917_114630",
   "axr": 11.634818881420868,
   "signed_pure": -0.29758860430058576,
   "signed_thick": -0.36929007975123795,
   "abs_pure": 0.29758860430058576,
   "abs_thick": 0.36929007975123795,
   "spearman_w_q": 1.0,
   "w_median_rel": 0.06951022339570799,
   "n_bins": 6
  },
  {
   "catalog": "GWTC-3",
   "event": "GW190924_021846",
   "axr": 6.978113923413571,
   "signed_pure": -0.5219995417891141,
   "signed_thick": 0.27765044532154093,
   "abs_pure": 0.5219995417891141,
   "abs_thick": 0.27765044532154093,
   "spearman_w_q": 1.0,
   "w_median_rel": 0.11709299086922749,
   "n_bins": 6
  },
  {
   "catalog": "GWTC-3",
   "event": "GW190925_232845",
   "axr": 3.424204585135956,
   "signed_pure": -1.9496045088268659,
   "signed_thick": -1.6044478113635705,
   "abs_pure": 1.9496045088268659,
   "abs_thick": 1.6044478113635705,
   "spearman_w_q": 1.0,
   "w_median_rel": 0.38709751768683526,
   "n_bins": 6
  },
  {
   "catalog": "GWTC-3",
   "event": "GW190930_133541",
   "axr": 6.809898782870291,
   "signed_pure": -0.7251884251244576,
   "signed_thick": -0.6902683847114304,
   "abs_pure": 0.7251884251244576,
   "abs_thick": 0.6902683847114304,
   "spearman_w_q": 1.0,
   "w_median_rel": 0.13676665430095192,
   "n_bins": 6
  },
  {
   "catalog": "GWTC-3",
   "event": "GW191103_012549",
   "axr": 4.582666331404841,
   "signed_pure": -1.094182342664169,
   "signed_thick": -0.0886588946165432,
   "abs_pure": 1.094182342664169,
   "abs_thick": 0.0886588946165432,
   "spearman_w_q": 0.942857142857143,
   "w_median_rel": 0.2850059137613686,
   "n_bins": 6
  },
  {
   "catalog": "GWTC-3",
   "event": "GW191105_143521",
   "axr": 3.7784141640656794,
   "signed_pure": -0.7147208923065307,
   "signed_thick": -0.6747665314567257,
   "abs_pure": 0.7147208923065307,
   "abs_thick": 0.6747665314567257,
   "spearman_w_q": 0.942857142857143,
   "w_median_rel": 0.38117337590901845,
   "n_bins": 6
  },
  {
   "catalog": "GWTC-3",
   "event": "GW191113_071753",
   "axr": 7.995185493689204,
   "signed_pure": -1.2024950952151698,
   "signed_thick": -1.2432092104494643,
   "abs_pure": 1.2024950952151698,
   "abs_thick": 1.2432092104494643,
   "spearman_w_q": 0.942857142857143,
   "w_median_rel": 0.10468652784241259,
   "n_bins": 6
  },
  {
   "catalog": "GWTC-3",
   "event": "GW191126_115259",
   "axr": 3.5142489514102406,
   "signed_pure": -2.141748836406009,
   "signed_thick": -1.0707023102714857,
   "abs_pure": 2.141748836406009,
   "abs_thick": 1.0707023102714857,
   "spearman_w_q": 1.0,
   "w_median_rel": 0.41303515568073434,
   "n_bins": 6
  },
  {
   "catalog": "GWTC-3",
   "event": "GW191129_134029",
   "axr": 5.767002148042432,
   "signed_pure": -0.37973083434098953,
   "signed_thick": -0.22213763350598015,
   "abs_pure": 0.37973083434098953,
   "abs_thick": 0.22213763350598015,
   "spearman_w_q": 1.0,
   "w_median_rel": 0.26600482975474904,
   "n_bins": 6
  },
  {
   "catalog": "GWTC-3",
   "event": "GW191204_171526",
   "axr": 5.457205768385802,
   "signed_pure": -0.2999435577113445,
   "signed_thick": -0.0416604948376289,
   "abs_pure": 0.2999435577113445,
   "abs_thick": 0.0416604948376289,
   "spearman_w_q": 1.0,
   "w_median_rel": 0.30186421928173635,
   "n_bins": 6
  },
  {
   "catalog": "GWTC-3",
   "event": "GW191216_213338",
   "axr": 6.743034652701128,
   "signed_pure": -0.37123763681347555,
   "signed_thick": 0.1475297996709628,
   "abs_pure": 0.37123763681347555,
   "abs_thick": 0.1475297996709628,
   "spearman_w_q": 0.942857142857143,
   "w_median_rel": 0.0863367489429377,
   "n_bins": 6
  },
  {
   "catalog": "GWTC-3",
   "event": "GW191219_163120",
   "axr": 43.96526613766357,
   "signed_pure": -0.7107378226266405,
   "signed_thick": -0.7132498599070232,
   "abs_pure": 0.7107378226266405,
   "abs_thick": 0.7132498599070232,
   "spearman_w_q": 0.942857142857143,
   "w_median_rel": 0.032220832505548726,
   "n_bins": 6
  },
  {
   "catalog": "GWTC-3",
   "event": "GW200115_042309",
   "axr": 13.122488967367401,
   "signed_pure": -0.21529181161886868,
   "signed_thick": -0.18719415548076768,
   "abs_pure": 0.21529181161886868,
   "abs_thick": 0.18719415548076768,
   "spearman_w_q": 1.0,
   "w_median_rel": 0.04305747728271907,
   "n_bins": 6
  },
  {
   "catalog": "GWTC-3",
   "event": "GW200129_065458",
   "axr": 3.064387948893478,
   "signed_pure": 12.694555854046257,
   "signed_thick": 13.259498103247807,
   "abs_pure": 12.694555854046257,
   "abs_thick": 13.259498103247807,
   "spearman_w_q": 0.942857142857143,
   "w_median_rel": 0.553680920196634,
   "n_bins": 6
  },
  {
   "catalog": "GWTC-3",
   "event": "GW200202_154313",
   "axr": 6.201115235007908,
   "signed_pure": -0.33355657138471884,
   "signed_thick": -0.03369868491120087,
   "abs_pure": 0.33355657138471884,
   "abs_thick": 0.03369868491120087,
   "spearman_w_q": 1.0,
   "w_median_rel": 0.15606549505164355,
   "n_bins": 6
  },
  {
   "catalog": "GWTC-3",
   "event": "GW200210_092254",
   "axr": 20.78335455735036,
   "signed_pure": -1.1899912278193483,
   "signed_thick": -1.214887063963431,
   "abs_pure": 1.1899912278193483,
   "abs_thick": 1.214887063963431,
   "spearman_w_q": 1.0,
   "w_median_rel": 0.07663664573490961,
   "n_bins": 6
  },
  {
   "catalog": "GWTC-3",
   "event": "GW200308_173609",
   "axr": 4.450071944505245,
   "signed_pure": -16.32416423390447,
   "signed_thick": -3.6800947407760702,
   "abs_pure": 16.32416423390447,
   "abs_thick": 3.6800947407760702,
   "spearman_w_q": 0.3142857142857143,
   "w_median_rel": 0.4830036655322274,
   "n_bins": 6
  },
  {
   "catalog": "GWTC-3",
   "event": "GW200316_215756",
   "axr": 6.828221269126653,
   "signed_pure": -1.57506453108536,
   "signed_thick": -1.1877719666647124,
   "abs_pure": 1.57506453108536,
   "abs_thick": 1.1877719666647124,
   "spearman_w_q": 1.0,
   "w_median_rel": 0.1919820379772392,
   "n_bins": 6
  },
  {
   "catalog": "GWTC-3",
   "event": "GW200322_091133",
   "axr": 8.791193867354501,
   "signed_pure": -5.695805191085128,
   "signed_thick": -4.941943338062032,
   "abs_pure": 5.695805191085128,
   "abs_thick": 4.941943338062032,
   "spearman_w_q": 1.0,
   "w_median_rel": 0.20601202591344295,
   "n_bins": 6
  },
  {
   "catalog": "O4a",
   "event": "GW230518_125908",
   "axr": 16.830653929602164,
   "signed_pure": -0.6065854533912045,
   "signed_thick": -0.5980764011812596,
   "abs_pure": 0.6065854533912045,
   "abs_thick": 0.5980764011812596,
   "spearman_w_q": 1.0,
   "w_median_rel": 0.08624411707096899,
   "n_bins": 6
  },
  {
   "catalog": "O4a",
   "event": "GW230529_181500",
   "axr": 10.366854783946819,
   "signed_pure": -0.29260952517856254,
   "signed_thick": -0.457469129211205,
   "abs_pure": 0.29260952517856254,
   "abs_thick": 0.457469129211205,
   "spearman_w_q": 1.0,
   "w_median_rel": 0.07750529856774765,
   "n_bins": 6
  },
  {
   "catalog": "O4a",
   "event": "GW230605_065343",
   "axr": 4.012931895666518,
   "signed_pure": -3.1165986196266715,
   "signed_thick": -2.729989994747285,
   "abs_pure": 3.1165986196266715,
   "abs_thick": 2.729989994747285,
   "spearman_w_q": 1.0,
   "w_median_rel": 0.44091494409080434,
   "n_bins": 6
  },
  {
   "catalog": "O4a",
   "event": "GW230627_015337",
   "axr": 8.317777340175319,
   "signed_pure": 0.24990114953237708,
   "signed_thick": 0.3194224422309446,
   "abs_pure": 0.24990114953237708,
   "abs_thick": 0.3194224422309446,
   "spearman_w_q": 0.942857142857143,
   "w_median_rel": 0.19709234107192466,
   "n_bins": 6
  },
  {
   "catalog": "O4a",
   "event": "GW230630_234532",
   "axr": 3.677784234444584,
   "signed_pure": -1.1711606780899046,
   "signed_thick": -0.9441613945268443,
   "abs_pure": 1.1711606780899046,
   "abs_thick": 0.9441613945268443,
   "spearman_w_q": 0.942857142857143,
   "w_median_rel": 0.45842535670351175,
   "n_bins": 6
  },
  {
   "catalog": "O4a",
   "event": "GW230702_185453",
   "axr": 3.4234775830365267,
   "signed_pure": 1.5868637991070784,
   "signed_thick": 2.1131758376839116,
   "abs_pure": 1.5868637991070784,
   "abs_thick": 2.1131758376839116,
   "spearman_w_q": 1.0,
   "w_median_rel": 0.4879267187542157,
   "n_bins": 6
  },
  {
   "catalog": "O4a",
   "event": "GW230729_082317",
   "axr": 4.394130735615992,
   "signed_pure": -1.256349912899907,
   "signed_thick": -1.0613112163206608,
   "abs_pure": 1.256349912899907,
   "abs_thick": 1.0613112163206608,
   "spearman_w_q": 1.0,
   "w_median_rel": 0.3510609870068187,
   "n_bins": 6
  },
  {
   "catalog": "O4a",
   "event": "GW230731_215307",
   "axr": 3.3690620274359206,
   "signed_pure": 0.2168513898688218,
   "signed_thick": 0.21318181821126814,
   "abs_pure": 0.2168513898688218,
   "abs_thick": 0.21318181821126814,
   "spearman_w_q": 0.942857142857143,
   "w_median_rel": 0.5158696783115393,
   "n_bins": 6
  },
  {
   "catalog": "O4a",
   "event": "GW230904_051013",
   "axr": 3.9093941105611334,
   "signed_pure": -1.2734541200746605,
   "signed_thick": -0.9945804196282495,
   "abs_pure": 1.2734541200746605,
   "abs_thick": 0.9945804196282495,
   "spearman_w_q": 0.942857142857143,
   "w_median_rel": 0.4100468106101314,
   "n_bins": 6
  },
  {
   "catalog": "O4a",
   "event": "GW231018_233037",
   "axr": 3.5298319528400914,
   "signed_pure": -2.317713752004323,
   "signed_thick": -1.5483080635088413,
   "abs_pure": 2.317713752004323,
   "abs_thick": 1.5483080635088413,
   "spearman_w_q": 1.0,
   "w_median_rel": 0.44317418836666295,
   "n_bins": 6
  },
  {
   "catalog": "O4a",
   "event": "GW231020_142947",
   "axr": 5.751729815519136,
   "signed_pure": 0.20298924776648164,
   "signed_thick": 0.5058255450987303,
   "abs_pure": 0.20298924776648164,
   "abs_thick": 0.5058255450987303,
   "spearman_w_q": 1.0,
   "w_median_rel": 0.2705595768744545,
   "n_bins": 6
  },
  {
   "catalog": "O4a",
   "event": "GW231104_133418",
   "axr": 3.3593351003102674,
   "signed_pure": -1.381856155226643,
   "signed_thick": -1.1925730913732764,
   "abs_pure": 1.381856155226643,
   "abs_thick": 1.1925730913732764,
   "spearman_w_q": 1.0,
   "w_median_rel": 0.4933022934634057,
   "n_bins": 6
  },
  {
   "catalog": "O4a",
   "event": "GW231113_200417",
   "axr": 4.073895242255616,
   "signed_pure": -2.1748059837221945,
   "signed_thick": -1.6753882649815068,
   "abs_pure": 2.1748059837221945,
   "abs_thick": 1.6753882649815068,
   "spearman_w_q": 1.0,
   "w_median_rel": 0.39446814996562674,
   "n_bins": 6
  },
  {
   "catalog": "O4a",
   "event": "GW231114_043211",
   "axr": 5.86868772977561,
   "signed_pure": -1.3991263239715295,
   "signed_thick": -1.2821805705391682,
   "abs_pure": 1.3991263239715295,
   "abs_thick": 1.2821805705391682,
   "spearman_w_q": 1.0,
   "w_median_rel": 0.2560987603382084,
   "n_bins": 6
  },
  {
   "catalog": "O4a",
   "event": "GW231118_005626",
   "axr": 3.3253650993502797,
   "signed_pure": -6.724951188788054,
   "signed_thick": -6.540672739472569,
   "abs_pure": 6.724951188788054,
   "abs_thick": 6.540672739472569,
   "spearman_w_q": 0.942857142857143,
   "w_median_rel": 0.4740422992939076,
   "n_bins": 6
  },
  {
   "catalog": "O4a",
   "event": "GW231118_090602",
   "axr": 7.56131510198953,
   "signed_pure": -0.5415329865266756,
   "signed_thick": -0.4728481916379792,
   "abs_pure": 0.5415329865266756,
   "abs_thick": 0.4728481916379792,
   "spearman_w_q": 1.0,
   "w_median_rel": 0.1713520799694472,
   "n_bins": 6
  },
  {
   "catalog": "O4a",
   "event": "GW231223_075055",
   "axr": 5.606623589584487,
   "signed_pure": -1.215881901686629,
   "signed_thick": -0.8835139629387356,
   "abs_pure": 1.215881901686629,
   "abs_thick": 0.8835139629387356,
   "spearman_w_q": 1.0,
   "w_median_rel": 0.24786366597827397,
   "n_bins": 6
  },
  {
   "catalog": "O4a",
   "event": "GW231223_202619",
   "axr": 3.260506000659365,
   "signed_pure": -3.2832612926213187,
   "signed_thick": -3.109716736686778,
   "abs_pure": 3.2832612926213187,
   "abs_thick": 3.109716736686778,
   "spearman_w_q": 0.942857142857143,
   "w_median_rel": 0.49068433546494106,
   "n_bins": 6
  },
  {
   "catalog": "O4a",
   "event": "GW231224_024321",
   "axr": 3.144110945204298,
   "signed_pure": -0.39372530672153516,
   "signed_thick": 0.2686534442915729,
   "abs_pure": 0.39372530672153516,
   "abs_thick": 0.2686534442915729,
   "spearman_w_q": 1.0,
   "w_median_rel": 0.5510576643010627,
   "n_bins": 6
  },
  {
   "catalog": "O4b",
   "event": "GW240413_022019",
   "axr": 6.369841448308633,
   "signed_pure": 0.5596926197520418,
   "signed_thick": 0.6584065834628632,
   "abs_pure": 0.5596926197520418,
   "abs_thick": 0.6584065834628632,
   "spearman_w_q": 1.0,
   "w_median_rel": 0.25371005345057684,
   "n_bins": 6
  },
  {
   "catalog": "O4b",
   "event": "GW240428_225440",
   "axr": 4.581977464451395,
   "signed_pure": 1.2379980485883948,
   "signed_thick": 1.3537911090305386,
   "abs_pure": 1.2379980485883948,
   "abs_thick": 1.3537911090305386,
   "spearman_w_q": 1.0,
   "w_median_rel": 0.3943764539032118,
   "n_bins": 6
  },
  {
   "catalog": "O4b",
   "event": "GW240507_041632",
   "axr": 4.676669623633093,
   "signed_pure": 3.6185320123232145,
   "signed_thick": 3.638343716699609,
   "abs_pure": 3.6185320123232145,
   "abs_thick": 3.638343716699609,
   "spearman_w_q": 1.0,
   "w_median_rel": 0.2361486170886972,
   "n_bins": 6
  },
  {
   "catalog": "O4b",
   "event": "GW240512_024139",
   "axr": 3.8695569655685857,
   "signed_pure": -1.3678153234848764,
   "signed_thick": -1.3743453128420526,
   "abs_pure": 1.3678153234848764,
   "abs_thick": 1.3743453128420526,
   "spearman_w_q": 0.942857142857143,
   "w_median_rel": 0.44575913590204197,
   "n_bins": 6
  },
  {
   "catalog": "O4b",
   "event": "GW240520_213616",
   "axr": 3.0846764663810573,
   "signed_pure": -2.3642136284987316,
   "signed_thick": -2.268229640346931,
   "abs_pure": 2.3642136284987316,
   "abs_thick": 2.268229640346931,
   "spearman_w_q": 0.942857142857143,
   "w_median_rel": 0.6071284533913787,
   "n_bins": 6
  },
  {
   "catalog": "O4b",
   "event": "GW240527_230910",
   "axr": 7.01663666875991,
   "signed_pure": 0.6266420833796644,
   "signed_thick": 0.5881266008528883,
   "abs_pure": 0.6266420833796644,
   "abs_thick": 0.5881266008528883,
   "spearman_w_q": 1.0,
   "w_median_rel": 0.1997100974676412,
   "n_bins": 6
  },
  {
   "catalog": "O4b",
   "event": "GW240530_012417",
   "axr": 4.436898148642945,
   "signed_pure": -0.17363222215971064,
   "signed_thick": 0.2545037474215235,
   "abs_pure": 0.17363222215971064,
   "abs_thick": 0.2545037474215235,
   "spearman_w_q": 1.0,
   "w_median_rel": 0.34922763938222556,
   "n_bins": 6
  },
  {
   "catalog": "O4b",
   "event": "GW240601_231004",
   "axr": 3.146319439178306,
   "signed_pure": 0.059254457700376406,
   "signed_thick": 0.6327893318648137,
   "abs_pure": 0.059254457700376406,
   "abs_thick": 0.6327893318648137,
   "spearman_w_q": 1.0,
   "w_median_rel": 0.5161367437875551,
   "n_bins": 6
  },
  {
   "catalog": "O4b",
   "event": "GW240622_004008",
   "axr": 4.282403898263288,
   "signed_pure": -0.6024826416180247,
   "signed_thick": -0.2753808282453747,
   "abs_pure": 0.6024826416180247,
   "abs_thick": 0.2753808282453747,
   "spearman_w_q": 1.0,
   "w_median_rel": 0.3779891369392972,
   "n_bins": 6
  },
  {
   "catalog": "O4b",
   "event": "GW240627_131622",
   "axr": 3.9804468640126704,
   "signed_pure": -0.6018403814216242,
   "signed_thick": -0.11259296378420913,
   "abs_pure": 0.6018403814216242,
   "abs_thick": 0.11259296378420913,
   "spearman_w_q": 1.0,
   "w_median_rel": 0.43564560757521836,
   "n_bins": 6
  },
  {
   "catalog": "O4b",
   "event": "GW240629_145256",
   "axr": 3.444782746314098,
   "signed_pure": -1.6070569346282468,
   "signed_thick": -1.5525903886822618,
   "abs_pure": 1.6070569346282468,
   "abs_thick": 1.5525903886822618,
   "spearman_w_q": 0.942857142857143,
   "w_median_rel": 0.5339484466492115,
   "n_bins": 6
  },
  {
   "catalog": "O4b",
   "event": "GW240825_055146",
   "axr": 3.846369488501976,
   "signed_pure": -1.3736526896554722,
   "signed_thick": -0.22214959004870138,
   "abs_pure": 1.3736526896554722,
   "abs_thick": 0.22214959004870138,
   "spearman_w_q": 1.0,
   "w_median_rel": 0.42844847162318533,
   "n_bins": 6
  },
  {
   "catalog": "O4b",
   "event": "GW240830_211120",
   "axr": 3.5281351731091575,
   "signed_pure": -2.670602161719472,
   "signed_thick": -2.0734403034416005,
   "abs_pure": 2.670602161719472,
   "abs_thick": 2.0734403034416005,
   "spearman_w_q": 1.0,
   "w_median_rel": 0.5375153398440063,
   "n_bins": 6
  },
  {
   "catalog": "O4b",
   "event": "GW240910_103535",
   "axr": 6.035111853494047,
   "signed_pure": -0.021295274186797997,
   "signed_thick": 0.16899550818345688,
   "abs_pure": 0.021295274186797997,
   "abs_thick": 0.16899550818345688,
   "spearman_w_q": 1.0,
   "w_median_rel": 0.2598669648042423,
   "n_bins": 6
  },
  {
   "catalog": "O4b",
   "event": "GW240915_001357",
   "axr": 5.011013806648295,
   "signed_pure": -0.013798278508886597,
   "signed_thick": -0.1361108735413552,
   "abs_pure": 0.013798278508886597,
   "abs_thick": 0.1361108735413552,
   "spearman_w_q": 1.0,
   "w_median_rel": 0.3248238907449605,
   "n_bins": 6
  },
  {
   "catalog": "O4b",
   "event": "GW240915_105151",
   "axr": 5.507073085713072,
   "signed_pure": 0.8696860592528992,
   "signed_thick": 1.0474844886981316,
   "abs_pure": 0.8696860592528992,
   "abs_thick": 1.0474844886981316,
   "spearman_w_q": 1.0,
   "w_median_rel": 0.278239643709621,
   "n_bins": 6
  },
  {
   "catalog": "O4b",
   "event": "GW240920_073424",
   "axr": 3.580759913697068,
   "signed_pure": -1.1375515776368843,
   "signed_thick": -0.8081931300572478,
   "abs_pure": 1.1375515776368843,
   "abs_thick": 0.8081931300572478,
   "spearman_w_q": 1.0,
   "w_median_rel": 0.48851295606249867,
   "n_bins": 6
  },
  {
   "catalog": "O4b",
   "event": "GW240921_201835",
   "axr": 5.630440385214587,
   "signed_pure": -2.3715949893808386,
   "signed_thick": -2.472277127712829,
   "abs_pure": 2.3715949893808386,
   "abs_thick": 2.472277127712829,
   "spearman_w_q": 1.0,
   "w_median_rel": 0.23403799338615788,
   "n_bins": 6
  },
  {
   "catalog": "O4b",
   "event": "GW240922_142106",
   "axr": 3.7879650099899185,
   "signed_pure": -1.3864056318832638,
   "signed_thick": -1.4551297028623082,
   "abs_pure": 1.3864056318832638,
   "abs_thick": 1.4551297028623082,
   "spearman_w_q": 0.942857142857143,
   "w_median_rel": 0.4749211238015313,
   "n_bins": 6
  },
  {
   "catalog": "O4b",
   "event": "GW240925_005809",
   "axr": 6.501564543647212,
   "signed_pure": 1.6039404043590935,
   "signed_thick": 1.7123135144415755,
   "abs_pure": 1.6039404043590935,
   "abs_thick": 1.7123135144415755,
   "spearman_w_q": 1.0,
   "w_median_rel": 0.26267394394949584,
   "n_bins": 6
  },
  {
   "catalog": "O4b",
   "event": "GW240930_035959",
   "axr": 4.304732394497918,
   "signed_pure": -2.894978799889543,
   "signed_thick": -2.7170445922397164,
   "abs_pure": 2.894978799889543,
   "abs_thick": 2.7170445922397164,
   "spearman_w_q": 1.0,
   "w_median_rel": 0.39261579576969163,
   "n_bins": 6
  },
  {
   "catalog": "O4b",
   "event": "GW241009_084816",
   "axr": 3.044584818902337,
   "signed_pure": -0.7722499171197228,
   "signed_thick": 0.009640178144195488,
   "abs_pure": 0.7722499171197228,
   "abs_thick": 0.009640178144195488,
   "spearman_w_q": 1.0,
   "w_median_rel": 0.6092542038897492,
   "n_bins": 6
  },
  {
   "catalog": "O4b",
   "event": "GW241011_233834",
   "axr": 29.343802710967605,
   "signed_pure": 0.07561112228387401,
   "signed_thick": 0.09819103729640233,
   "abs_pure": 0.07561112228387401,
   "abs_thick": 0.09819103729640233,
   "spearman_w_q": 1.0,
   "w_median_rel": 0.03570389933272371,
   "n_bins": 6
  },
  {
   "catalog": "O4b",
   "event": "GW241102_124058",
   "axr": 8.247920566358433,
   "signed_pure": 0.5658519012116869,
   "signed_thick": 0.5563733913157591,
   "abs_pure": 0.5658519012116869,
   "abs_thick": 0.5563733913157591,
   "spearman_w_q": 0.942857142857143,
   "w_median_rel": 0.18594351522642408,
   "n_bins": 6
  },
  {
   "catalog": "O4b",
   "event": "GW241109_115924",
   "axr": 4.835091365959454,
   "signed_pure": -0.9057499151354307,
   "signed_thick": -0.9331796035552316,
   "abs_pure": 0.9057499151354307,
   "abs_thick": 0.9331796035552316,
   "spearman_w_q": 0.942857142857143,
   "w_median_rel": 0.32160298549057653,
   "n_bins": 6
  },
  {
   "catalog": "O4b",
   "event": "GW241110_124123",
   "axr": 6.519969362489334,
   "signed_pure": -1.3164918255402824,
   "signed_thick": -1.2926624809830116,
   "abs_pure": 1.3164918255402824,
   "abs_thick": 1.2926624809830116,
   "spearman_w_q": 1.0,
   "w_median_rel": 0.23212418938397664,
   "n_bins": 6
  },
  {
   "catalog": "O4b",
   "event": "GW241114_235258",
   "axr": 3.6679637352522994,
   "signed_pure": -0.5927028345759027,
   "signed_thick": -0.42094110000400065,
   "abs_pure": 0.5927028345759027,
   "abs_thick": 0.42094110000400065,
   "spearman_w_q": 1.0,
   "w_median_rel": 0.4576728519439714,
   "n_bins": 6
  },
  {
   "catalog": "O4b",
   "event": "GW241130_110422",
   "axr": 3.7898159110969143,
   "signed_pure": -1.6386408440564821,
   "signed_thick": -1.4926478154463894,
   "abs_pure": 1.6386408440564821,
   "abs_thick": 1.4926478154463894,
   "spearman_w_q": 1.0,
   "w_median_rel": 0.43466299334962016,
   "n_bins": 6
  },
  {
   "catalog": "O4b",
   "event": "GW241225_042553",
   "axr": 4.890907763607683,
   "signed_pure": -2.2790430502174672,
   "signed_thick": -2.2745743968300474,
   "abs_pure": 2.2790430502174672,
   "abs_thick": 2.2745743968300474,
   "spearman_w_q": 0.6,
   "w_median_rel": 0.3696971909499763,
   "n_bins": 6
  },
  {
   "catalog": "O4b",
   "event": "GW241231_054133",
   "axr": 5.577859164231567,
   "signed_pure": 0.8653853390144093,
   "signed_thick": 0.956842442456292,
   "abs_pure": 0.8653853390144093,
   "abs_thick": 0.956842442456292,
   "spearman_w_q": 1.0,
   "w_median_rel": 0.3173970325055684,
   "n_bins": 6
  },
  {
   "catalog": "O4b",
   "event": "GW250118_055802",
   "axr": 3.79054256930562,
   "signed_pure": -1.303752266281947,
   "signed_thick": -0.9119575432798115,
   "abs_pure": 1.303752266281947,
   "abs_thick": 0.9119575432798115,
   "spearman_w_q": 1.0,
   "w_median_rel": 0.38566486290034496,
   "n_bins": 6
  },
  {
   "catalog": "O4b",
   "event": "GW250119_190238",
   "axr": 3.2766849127835993,
   "signed_pure": 2.32575966618208,
   "signed_thick": 2.1247422375180918,
   "abs_pure": 2.32575966618208,
   "abs_thick": 2.1247422375180918,
   "spearman_w_q": -0.942857142857143,
   "w_median_rel": 0.5238604366866626,
   "n_bins": 6
  }
 ],
 "events_cross_family": [
  {
   "catalog": "GWTC-3",
   "event": "GW190412",
   "axr_A": 9.08810918468101,
   "axr_B": 6.503639448438207,
   "AtoB_measured": 1.4350162421395964,
   "AtoB_constant": 1.233111824815552,
   "AtoB_linear": 1.3199136862786816,
   "AtoB_quadratic": 1.256174007198581,
   "AtoB_pure": 1.3577109197881612,
   "BtoA_measured": 0.3760839368432016,
   "BtoA_constant": 0.43713293910954576,
   "BtoA_linear": 0.2523174126626486,
   "BtoA_quadratic": 0.3268159847034724,
   "BtoA_pure": 0.2982744446128436
  },
  {
   "catalog": "GWTC-3",
   "event": "GW190512_180714",
   "axr_A": 3.9723132388396265,
   "axr_B": 3.225631874281295,
   "AtoB_measured": 1.7996676220148515,
   "AtoB_constant": 2.081135666333495,
   "AtoB_linear": 2.3041411986283435,
   "AtoB_quadratic": 1.6280338608400484,
   "AtoB_pure": 2.1225255949533732,
   "BtoA_measured": 0.31426695786433356,
   "BtoA_constant": 0.943645759096313,
   "BtoA_linear": 0.7975817879165561,
   "BtoA_quadratic": 0.4130194053124967,
   "BtoA_pure": 0.884911436491592
  },
  {
   "catalog": "GWTC-3",
   "event": "GW190708_232457",
   "axr_A": 4.184500518987541,
   "axr_B": 3.162531097115487,
   "AtoB_measured": 3.5855337053639005,
   "AtoB_constant": 3.4092035234210414,
   "AtoB_linear": 3.7482973486785625,
   "AtoB_quadratic": 2.9298024363264688,
   "AtoB_pure": 3.7081525551812433,
   "BtoA_measured": 0.3039415052379866,
   "BtoA_constant": 0.02729298785018841,
   "BtoA_linear": 0.4271603130183621,
   "BtoA_quadratic": 0.6833367805810724,
   "BtoA_pure": 0.10520645189603783
  },
  {
   "catalog": "GWTC-3",
   "event": "GW190720_000836",
   "axr_A": 6.76576719765828,
   "axr_B": 4.136549005165398,
   "AtoB_measured": 2.56439302677083,
   "AtoB_constant": 2.7018067642073618,
   "AtoB_linear": 2.580022933433469,
   "AtoB_quadratic": 2.5535876080712967,
   "AtoB_pure": 2.835604525834867,
   "BtoA_measured": 0.42313489095388945,
   "BtoA_constant": 0.2172298552948746,
   "BtoA_linear": 0.5743581181199318,
   "BtoA_quadratic": 0.0843604147586916,
   "BtoA_pure": 0.43623095602950457
  },
  {
   "catalog": "GWTC-3",
   "event": "GW190728_064510",
   "axr_A": 6.841991712423321,
   "axr_B": 5.36695368124839,
   "AtoB_measured": 0.8214456486834933,
   "AtoB_constant": 0.713646378089237,
   "AtoB_linear": 0.9098342333697929,
   "AtoB_quadratic": 0.39387090944268266,
   "AtoB_pure": 1.0095937044395953,
   "BtoA_measured": 0.7226143322199903,
   "BtoA_constant": 0.5072179722373562,
   "BtoA_linear": 0.47451280774336624,
   "BtoA_quadratic": 1.0946935856774758,
   "BtoA_pure": 0.8575230515863836
  },
  {
   "catalog": "GWTC-3",
   "event": "GW190924_021846",
   "axr_A": 7.926737790508639,
   "axr_B": 5.278360799510802,
   "AtoB_measured": 1.6546390883525532,
   "AtoB_constant": 1.8292934916273396,
   "AtoB_linear": 1.7190535278669756,
   "AtoB_quadratic": 1.5953782421932772,
   "AtoB_pure": 1.8775982176289006,
   "BtoA_measured": 0.12226271692861701,
   "BtoA_constant": 0.04764269812213229,
   "BtoA_linear": 0.2433707586994558,
   "BtoA_quadratic": 0.5565439398525598,
   "BtoA_pure": 0.21241163042279254
  },
  {
   "catalog": "GWTC-3",
   "event": "GW190930_133541",
   "axr_A": 7.342610715022573,
   "axr_B": 7.504779291582272,
   "AtoB_measured": 1.2235384714968518,
   "AtoB_constant": 1.0735070613854987,
   "AtoB_linear": 1.2869488672769194,
   "AtoB_quadratic": 1.2736011347202236,
   "AtoB_pure": 1.1475294322752347,
   "BtoA_measured": 0.6519410672834454,
   "BtoA_constant": 0.4862323739565966,
   "BtoA_linear": 0.8258552675561646,
   "BtoA_quadratic": 0.6121400997028843,
   "BtoA_pure": 0.6659098253611546
  },
  {
   "catalog": "GWTC-3",
   "event": "GW191103_012549",
   "axr_A": 4.912234203754999,
   "axr_B": 4.100780525816628,
   "AtoB_measured": 0.9676148146457422,
   "AtoB_constant": 0.8851903599762352,
   "AtoB_linear": 0.9223820433758192,
   "AtoB_quadratic": 0.34537059120623326,
   "AtoB_pure": 1.1520886233981287,
   "BtoA_measured": 0.3984720696469708,
   "BtoA_constant": 0.2358326508206119,
   "BtoA_linear": 0.9283721987632987,
   "BtoA_quadratic": 0.20531714708732807,
   "BtoA_pure": 0.6972757818689388
  },
  {
   "catalog": "GWTC-3",
   "event": "GW191105_143521",
   "axr_A": 4.2732572221826794,
   "axr_B": 3.0947745309570713,
   "AtoB_measured": 0.014367920742586193,
   "AtoB_constant": 0.4942188291398679,
   "AtoB_linear": 0.12044118718256414,
   "AtoB_quadratic": 0.8405432784582558,
   "AtoB_pure": 0.7439810265439348,
   "BtoA_measured": 0.6275096926173944,
   "BtoA_constant": 1.5333814798848948,
   "BtoA_linear": 1.2144886743517986,
   "BtoA_quadratic": 0.7802028698811796,
   "BtoA_pure": 0.9869453528124836
  },
  {
   "catalog": "GWTC-3",
   "event": "GW191113_071753",
   "axr_A": 7.831088571342759,
   "axr_B": 8.004491088424802,
   "AtoB_measured": 1.1326445057861747,
   "AtoB_constant": 1.1141610205385746,
   "AtoB_linear": 1.229213392823766,
   "AtoB_quadratic": 1.230798431176197,
   "AtoB_pure": 1.2450714225290085,
   "BtoA_measured": 1.183488813244253,
   "BtoA_constant": 1.0968965176580525,
   "BtoA_linear": 0.9345886149884564,
   "BtoA_quadratic": 0.8430064612707611,
   "BtoA_pure": 0.9555556185809166
  },
  {
   "catalog": "GWTC-3",
   "event": "GW191126_115259",
   "axr_A": 3.591521640687798,
   "axr_B": 3.54088554427627,
   "AtoB_measured": 0.639361748709149,
   "AtoB_constant": 0.17123294101037345,
   "AtoB_linear": 0.4561286709580088,
   "AtoB_quadratic": 1.31171008833212,
   "AtoB_pure": 1.3717535175770763,
   "BtoA_measured": 0.36537039498819013,
   "BtoA_constant": 0.7794155392426205,
   "BtoA_linear": 1.0224186909100013,
   "BtoA_quadratic": 1.2195506539908365,
   "BtoA_pure": 1.840120512704999
  },
  {
   "catalog": "GWTC-3",
   "event": "GW191129_134029",
   "axr_A": 5.974742379680363,
   "axr_B": 5.358336453742062,
   "AtoB_measured": 0.2983965369077737,
   "AtoB_constant": 0.4445156693145975,
   "AtoB_linear": 0.1727749888847825,
   "AtoB_quadratic": 0.3635731385286931,
   "AtoB_pure": 0.5298519033731282,
   "BtoA_measured": 0.21345892233355812,
   "BtoA_constant": 0.10238216247469722,
   "BtoA_linear": 0.21884206439241893,
   "BtoA_quadratic": 0.3833223638307288,
   "BtoA_pure": 0.2764936977043533
  },
  {
   "catalog": "GWTC-3",
   "event": "GW191204_171526",
   "axr_A": 6.171630714953116,
   "axr_B": 4.7425343254106735,
   "AtoB_measured": 0.2866686605420057,
   "AtoB_constant": 0.06379180453154731,
   "AtoB_linear": 0.179487989623766,
   "AtoB_quadratic": 0.20106116512150152,
   "AtoB_pure": 0.12460952873979636,
   "BtoA_measured": 0.18948613959167915,
   "BtoA_constant": 0.1003891556371741,
   "BtoA_linear": 0.0016233779678032079,
   "BtoA_quadratic": 0.029121025703489067,
   "BtoA_pure": 0.25179827025107215
  },
  {
   "catalog": "GWTC-3",
   "event": "GW191216_213338",
   "axr_A": 7.461685093273128,
   "axr_B": 6.629740854993348,
   "AtoB_measured": 0.6043919731343124,
   "AtoB_constant": 1.013725989724179,
   "AtoB_linear": 0.8315327908435961,
   "AtoB_quadratic": 0.2021706758815185,
   "AtoB_pure": 0.6680916475549168,
   "BtoA_measured": 0.10163938031755038,
   "BtoA_constant": 0.6059515634262027,
   "BtoA_linear": 0.548486538776018,
   "BtoA_quadratic": 0.2933781592421383,
   "BtoA_pure": 0.29670480807928357
  },
  {
   "catalog": "GWTC-3",
   "event": "GW200202_154313",
   "axr_A": 6.3723604177931445,
   "axr_B": 6.39038569000758,
   "AtoB_measured": 0.49012821664467765,
   "AtoB_constant": 0.7173239879524544,
   "AtoB_linear": 0.04830968077635589,
   "AtoB_quadratic": 0.013680814886669168,
   "AtoB_pure": 0.1785389346404429,
   "BtoA_measured": 1.1310175746145887,
   "BtoA_constant": 0.5115276388242478,
   "BtoA_linear": 0.4022490200152333,
   "BtoA_quadratic": 0.27350151858721006,
   "BtoA_pure": 0.43226457114067784
  },
  {
   "catalog": "GWTC-3",
   "event": "GW200210_092254",
   "axr_A": 24.15050543805209,
   "axr_B": 15.377575542191604,
   "AtoB_measured": 1.5887657777836637,
   "AtoB_constant": 1.6382342406291457,
   "AtoB_linear": 1.6635184845328297,
   "AtoB_quadratic": 1.6303303441069374,
   "AtoB_pure": 1.6453964146755027,
   "BtoA_measured": 1.0223064367141035,
   "BtoA_constant": 1.0201876530672962,
   "BtoA_linear": 1.0017387993912905,
   "BtoA_quadratic": 0.9780356958061702,
   "BtoA_pure": 1.0366840406252606
  },
  {
   "catalog": "GWTC-3",
   "event": "GW200316_215756",
   "axr_A": 7.950789178885301,
   "axr_B": 4.869044726788358,
   "AtoB_measured": 0.8951251372230615,
   "AtoB_constant": 1.7870828549853002,
   "AtoB_linear": 1.2472890104204168,
   "AtoB_quadratic": 1.6788881761846142,
   "AtoB_pure": 1.6446425351095968,
   "BtoA_measured": 0.9102492864332703,
   "BtoA_constant": 0.9414225120445678,
   "BtoA_linear": 1.2038550362331364,
   "BtoA_quadratic": 1.2494008869354047,
   "BtoA_pure": 1.1810502702613235
  },
  {
   "catalog": "O4a",
   "event": "GW230605_065343",
   "axr_A": 3.877889764167698,
   "axr_B": 4.132843552701701,
   "AtoB_measured": 2.8727931766373445,
   "AtoB_constant": 2.6400233571570197,
   "AtoB_linear": 2.66354719555477,
   "AtoB_quadratic": 2.744980173126123,
   "AtoB_pure": 2.954297354911546,
   "BtoA_measured": 2.7056380113625664,
   "BtoA_constant": 3.2578615315274533,
   "BtoA_linear": 3.062123145277411,
   "BtoA_quadratic": 3.0498479560950784,
   "BtoA_pure": 3.3139977113639816
  },
  {
   "catalog": "O4a",
   "event": "GW230627_015337",
   "axr_A": 8.62055882281009,
   "axr_B": 8.073678104668014,
   "AtoB_measured": 0.15281408954592735,
   "AtoB_constant": 0.04831626669985667,
   "AtoB_linear": 0.14964009033894854,
   "AtoB_quadratic": 0.16421010616571152,
   "AtoB_pure": 0.16015402945834012,
   "BtoA_measured": 0.4891658938183525,
   "BtoA_constant": 0.4431352776427957,
   "BtoA_linear": 0.3104556014816069,
   "BtoA_quadratic": 0.37157093727668666,
   "BtoA_pure": 0.3733439830753298
  },
  {
   "catalog": "O4a",
   "event": "GW230630_234532",
   "axr_A": 3.680578804871945,
   "axr_B": 3.6720834250076653,
   "AtoB_measured": 0.8351634632809919,
   "AtoB_constant": 0.9196747918536516,
   "AtoB_linear": 0.27899314008399756,
   "AtoB_quadratic": 0.7435798763553123,
   "AtoB_pure": 1.2656865148603913,
   "BtoA_measured": 0.7552798961398821,
   "BtoA_constant": 0.8868745397275575,
   "BtoA_linear": 1.0147457507580668,
   "BtoA_quadratic": 0.9420009547149562,
   "BtoA_pure": 1.0710960600074486
  },
  {
   "catalog": "O4a",
   "event": "GW230702_185453",
   "axr_A": 3.5920461712525875,
   "axr_B": 3.2498236084004124,
   "AtoB_measured": 1.7681962305587433,
   "AtoB_constant": 1.3047085962726044,
   "AtoB_linear": 1.9770663943295403,
   "AtoB_quadratic": 1.7016936069784663,
   "AtoB_pure": 1.1712817858691267,
   "BtoA_measured": 3.3015958677989943,
   "BtoA_constant": 3.0872707947016806,
   "BtoA_linear": 3.333935839950726,
   "BtoA_quadratic": 3.3047227806410717,
   "BtoA_pure": 2.963301048253271
  },
  {
   "catalog": "O4a",
   "event": "GW230729_082317",
   "axr_A": 4.686293581440379,
   "axr_B": 4.087094011849224,
   "AtoB_measured": 0.6866180165038145,
   "AtoB_constant": 0.8090954189488571,
   "AtoB_linear": 0.7579358924321298,
   "AtoB_quadratic": 0.8385570915642404,
   "AtoB_pure": 1.2122538419502575,
   "BtoA_measured": 0.5636917027527772,
   "BtoA_constant": 1.1532588121051788,
   "BtoA_linear": 0.628877925214681,
   "BtoA_quadratic": 1.4666802858347694,
   "BtoA_pure": 1.3156136373872584
  },
  {
   "catalog": "O4a",
   "event": "GW230731_215307",
   "axr_A": 3.384026712392205,
   "axr_B": 3.355120699649159,
   "AtoB_measured": 0.8971853065398534,
   "AtoB_constant": 0.5253039190043296,
   "AtoB_linear": 0.7859009486954278,
   "AtoB_quadratic": 0.7038471142451499,
   "AtoB_pure": 0.32728165685719546,
   "BtoA_measured": 1.1408500811305373,
   "BtoA_constant": 0.4082063469896866,
   "BtoA_linear": 0.37676338310146207,
   "BtoA_quadratic": 0.9379339222328724,
   "BtoA_pure": 0.10141661784538769
  },
  {
   "catalog": "O4a",
   "event": "GW230904_051013",
   "axr_A": 4.019372797971076,
   "axr_B": 3.7881446636884615,
   "AtoB_measured": 0.5515012882257793,
   "AtoB_constant": 0.509045445689253,
   "AtoB_linear": 0.8264717081360118,
   "AtoB_quadratic": 1.0424081025071814,
   "AtoB_pure": 1.1913712198091844,
   "BtoA_measured": 0.7838983503462487,
   "BtoA_constant": 0.7647342454276895,
   "BtoA_linear": 0.8291363208283258,
   "BtoA_quadratic": 1.042473089786995,
   "BtoA_pure": 1.3437300837921669
  },
  {
   "catalog": "O4a",
   "event": "GW231018_233037",
   "axr_A": 3.610437490040496,
   "axr_B": 3.4441539526466545,
   "AtoB_measured": 1.993060991266674,
   "AtoB_constant": 2.8361254573688655,
   "AtoB_linear": 1.6050070007733268,
   "AtoB_quadratic": 2.7366758825776856,
   "AtoB_pure": 2.503867458000201,
   "BtoA_measured": 1.2070377122986429,
   "BtoA_constant": 1.1240264071381034,
   "BtoA_linear": 1.7396851825943145,
   "BtoA_quadratic": 1.4217510041824823,
   "BtoA_pure": 2.1267202592580077
  },
  {
   "catalog": "O4a",
   "event": "GW231020_142947",
   "axr_A": 5.676069090413399,
   "axr_B": 5.894077383038515,
   "AtoB_measured": 0.32891951747271264,
   "AtoB_constant": 0.4003841266833206,
   "AtoB_linear": 0.37660862319779653,
   "AtoB_quadratic": 0.5585795244381018,
   "AtoB_pure": 0.1396627349376729,
   "BtoA_measured": 0.7030316035253179,
   "BtoA_constant": 0.3595931775047916,
   "BtoA_linear": 0.7755568905153325,
   "BtoA_quadratic": 0.4763447731309327,
   "BtoA_pure": 0.24060562891153836
  },
  {
   "catalog": "O4a",
   "event": "GW231104_133418",
   "axr_A": 3.2649894826486867,
   "axr_B": 3.4549312437903197,
   "AtoB_measured": 0.9184908444185282,
   "AtoB_constant": 1.2904376352174722,
   "AtoB_linear": 1.733753842269607,
   "AtoB_quadratic": 1.063816363934535,
   "AtoB_pure": 1.9030026155789699,
   "BtoA_measured": 0.2411747789143135,
   "BtoA_constant": 0.609809298485402,
   "BtoA_linear": 0.03975111021856037,
   "BtoA_quadratic": 0.27836170041518926,
   "BtoA_pure": 0.8726481325856241
  },
  {
   "catalog": "O4a",
   "event": "GW231113_200417",
   "axr_A": 3.7084186519199944,
   "axr_B": 4.4075539666454695,
   "AtoB_measured": 1.5662731667740672,
   "AtoB_constant": 1.9996537155409726,
   "AtoB_linear": 1.4668278984055405,
   "AtoB_quadratic": 2.028187456302561,
   "AtoB_pure": 2.112819556434573,
   "BtoA_measured": 1.7514900463893355,
   "BtoA_constant": 1.641613179159208,
   "BtoA_linear": 2.0145027301412313,
   "BtoA_quadratic": 1.5383920667592008,
   "BtoA_pure": 2.2606184237058073
  },
  {
   "catalog": "O4a",
   "event": "GW231114_043211",
   "axr_A": 5.852470845311972,
   "axr_B": 5.905006793957307,
   "AtoB_measured": 0.7227672985858646,
   "AtoB_constant": 0.8232913634439853,
   "AtoB_linear": 1.0615080820622325,
   "AtoB_quadratic": 0.9900198743552835,
   "AtoB_pure": 1.112533986737219,
   "BtoA_measured": 1.5092597615284262,
   "BtoA_constant": 1.6939168557924518,
   "BtoA_linear": 1.5629017621446053,
   "BtoA_quadratic": 1.513357368740941,
   "BtoA_pure": 1.699908091349016
  },
  {
   "catalog": "O4a",
   "event": "GW231118_090602",
   "axr_A": 9.109272523862098,
   "axr_B": 4.970218688853002,
   "AtoB_measured": 1.064467230118936,
   "AtoB_constant": 1.6530953188385524,
   "AtoB_linear": 1.2698814431161054,
   "AtoB_quadratic": 1.4976184700744568,
   "AtoB_pure": 1.6228737490319816,
   "BtoA_measured": 0.38723307236298865,
   "BtoA_constant": 0.3676067529350746,
   "BtoA_linear": 0.24097959562720916,
   "BtoA_quadratic": 0.26292235604663006,
   "BtoA_pure": 0.33515452133514145
  },
  {
   "catalog": "O4a",
   "event": "GW231223_075055",
   "axr_A": 5.557714514587965,
   "axr_B": 5.658458816945227,
   "AtoB_measured": 0.8085774299646005,
   "AtoB_constant": 1.2891360866545085,
   "AtoB_linear": 0.9440916309172849,
   "AtoB_quadratic": 1.2731732082148994,
   "AtoB_pure": 1.156605075799888,
   "BtoA_measured": 1.3521736494440972,
   "BtoA_constant": 1.2117096469546027,
   "BtoA_linear": 0.8807261326349192,
   "BtoA_quadratic": 1.1407186369573878,
   "BtoA_pure": 1.2615585260217586
  },
  {
   "catalog": "O4a",
   "event": "GW231223_202619",
   "axr_A": 3.3682722037110304,
   "axr_B": 3.1347519050836246,
   "AtoB_measured": 2.65708001094643,
   "AtoB_constant": 2.4431999113498932,
   "AtoB_linear": 3.697901574854825,
   "AtoB_quadratic": 2.928994696880835,
   "AtoB_pure": 3.646366252162295,
   "BtoA_measured": 1.9546754699909457,
   "BtoA_constant": 2.425052263945588,
   "BtoA_linear": 1.8574593602054108,
   "BtoA_quadratic": 2.235075629636924,
   "BtoA_pure": 2.9295549205801876
  },
  {
   "catalog": "O4a",
   "event": "GW231224_024321",
   "axr_A": 3.19774684298446,
   "axr_B": 3.0774323427826737,
   "AtoB_measured": 0.21893507454649352,
   "AtoB_constant": 0.35757379513671594,
   "AtoB_linear": 0.13816723189040658,
   "AtoB_quadratic": 0.11384244751872075,
   "AtoB_pure": 0.2096638639852415,
   "BtoA_measured": 0.6094243769005914,
   "BtoA_constant": 0.34990947060916255,
   "BtoA_linear": 0.17329165848892103,
   "BtoA_quadratic": 0.01893680097495576,
   "BtoA_pure": 0.5546514759055015
  },
  {
   "catalog": "O4b",
   "event": "GW240413_022019",
   "axr_A": 7.0778219859672475,
   "axr_B": 6.369841448308633,
   "AtoB_measured": 0.8805352060412588,
   "AtoB_constant": 0.8024947322651599,
   "AtoB_linear": 0.8018241315156729,
   "AtoB_quadratic": 0.6709133633907811,
   "AtoB_pure": 0.5596926197520418,
   "BtoA_measured": 0.47621067503231984,
   "BtoA_constant": 0.3842463767882407,
   "BtoA_linear": 0.6868882551384559,
   "BtoA_quadratic": 0.6865770996394644,
   "BtoA_pure": 0.3518487583882859
  },
  {
   "catalog": "O4b",
   "event": "GW240428_225440",
   "axr_A": 4.713845729175201,
   "axr_B": 4.581977464451395,
   "AtoB_measured": 1.3881144586347034,
   "AtoB_constant": 1.14403846402584,
   "AtoB_linear": 1.3792173620009578,
   "AtoB_quadratic": 1.2881959500559788,
   "AtoB_pure": 1.2379980485883948,
   "BtoA_measured": 1.5839053235583265,
   "BtoA_constant": 1.8930639768127264,
   "BtoA_linear": 1.5348842254409476,
   "BtoA_quadratic": 1.8739487893957403,
   "BtoA_pure": 1.495969615570374
  },
  {
   "catalog": "O4b",
   "event": "GW240507_041632",
   "axr_A": 4.637171961669814,
   "axr_B": 4.676669623633093,
   "AtoB_measured": 3.6869641087353955,
   "AtoB_constant": 3.5844749823553173,
   "AtoB_linear": 3.780973894930412,
   "AtoB_quadratic": 3.7528742431994147,
   "AtoB_pure": 3.6185320123232145,
   "BtoA_measured": 2.8490065268725004,
   "BtoA_constant": 2.788011627364966,
   "BtoA_linear": 2.9961203637255664,
   "BtoA_quadratic": 2.7465932397876713,
   "BtoA_pure": 2.8087625224455337
  },
  {
   "catalog": "O4b",
   "event": "GW240512_024139",
   "axr_A": 4.88822437062902,
   "axr_B": 3.8695569655685857,
   "AtoB_measured": 1.0553858062127972,
   "AtoB_constant": 0.5734130039680281,
   "AtoB_linear": 0.9091417431183402,
   "AtoB_quadratic": 0.7415965052919944,
   "AtoB_pure": 1.3678153234848764,
   "BtoA_measured": 0.3882829460833648,
   "BtoA_constant": 0.6544495389687199,
   "BtoA_linear": 0.42829443492379937,
   "BtoA_quadratic": 0.6202778382867109,
   "BtoA_pure": 0.783342372761183
  },
  {
   "catalog": "O4b",
   "event": "GW240520_213616",
   "axr_A": 3.560096101635664,
   "axr_B": 3.0846764663810573,
   "AtoB_measured": 2.331061441995672,
   "AtoB_constant": 2.028411105707164,
   "AtoB_linear": 2.0000422546106336,
   "AtoB_quadratic": 2.175733181242208,
   "AtoB_pure": 2.3642136284987316,
   "BtoA_measured": 1.7927353272759774,
   "BtoA_constant": 1.69824849667404,
   "BtoA_linear": 1.7618108403617896,
   "BtoA_quadratic": 1.4238733487273123,
   "BtoA_pure": 2.0122638443449716
  },
  {
   "catalog": "O4b",
   "event": "GW240527_230910",
   "axr_A": 7.567323337245572,
   "axr_B": 7.01663666875991,
   "AtoB_measured": 0.6242247490414741,
   "AtoB_constant": 0.6111448761937481,
   "AtoB_linear": 0.5037574748284328,
   "AtoB_quadratic": 0.7961952806736008,
   "AtoB_pure": 0.6266420833796644,
   "BtoA_measured": 0.46965385174485164,
   "BtoA_constant": 0.13517554763865292,
   "BtoA_linear": 0.4732942023302371,
   "BtoA_quadratic": 0.4467585621963224,
   "BtoA_pure": 0.28723394231204225
  },
  {
   "catalog": "O4b",
   "event": "GW240530_012417",
   "axr_A": 5.30941074827359,
   "axr_B": 4.436898148642945,
   "AtoB_measured": 0.1515327679405516,
   "AtoB_constant": 0.3479787059541479,
   "AtoB_linear": 0.13900426910626607,
   "AtoB_quadratic": 0.49474205613009303,
   "AtoB_pure": 0.17363222215971064,
   "BtoA_measured": 1.057002187431749,
   "BtoA_constant": 0.6237698338223368,
   "BtoA_linear": 0.42882275171075435,
   "BtoA_quadratic": 0.9945610551948789,
   "BtoA_pure": 0.3456943557901013
  },
  {
   "catalog": "O4b",
   "event": "GW240601_231004",
   "axr_A": 4.005653746075971,
   "axr_B": 3.146319439178306,
   "AtoB_measured": 0.5003853066508555,
   "AtoB_constant": 0.8437215078151894,
   "AtoB_linear": 0.38954510941047715,
   "AtoB_quadratic": 0.6198965533261287,
   "AtoB_pure": 0.059254457700376406,
   "BtoA_measured": 1.1330512969080928,
   "BtoA_constant": 1.8106552357961334,
   "BtoA_linear": 1.9476280163751483,
   "BtoA_quadratic": 1.6999259236834803,
   "BtoA_pure": 1.2659619082531606
  },
  {
   "catalog": "O4b",
   "event": "GW240622_004008",
   "axr_A": 4.352067863805167,
   "axr_B": 4.282403898263288,
   "AtoB_measured": 0.113823131409589,
   "AtoB_constant": 0.3017159418762674,
   "AtoB_linear": 0.1237359623128782,
   "AtoB_quadratic": 0.3151821934592931,
   "AtoB_pure": 0.6024826416180247,
   "BtoA_measured": 0.12979123559574646,
   "BtoA_constant": 0.3727232951309247,
   "BtoA_linear": 0.33188018713713063,
   "BtoA_quadratic": 0.35192075484903285,
   "BtoA_pure": 0.05474823728383171
  },
  {
   "catalog": "O4b",
   "event": "GW240627_131622",
   "axr_A": 5.016317611047333,
   "axr_B": 3.9804468640126704,
   "AtoB_measured": 0.24222639103052757,
   "AtoB_constant": 0.7314201192517658,
   "AtoB_linear": 0.04711447518681666,
   "AtoB_quadratic": 0.46477414848720855,
   "AtoB_pure": 0.6018403814216242,
   "BtoA_measured": 0.07426285323506931,
   "BtoA_constant": 0.0035305954527018457,
   "BtoA_linear": 0.41043816113744924,
   "BtoA_quadratic": 0.12454730629724509,
   "BtoA_pure": 0.3017949229569865
  },
  {
   "catalog": "O4b",
   "event": "GW240629_145256",
   "axr_A": 3.738230081642744,
   "axr_B": 3.444782746314098,
   "AtoB_measured": 1.0825622185303985,
   "AtoB_constant": 1.1680156192136906,
   "AtoB_linear": 1.2648280942129588,
   "AtoB_quadratic": 1.3685766251500695,
   "AtoB_pure": 1.6070569346282468,
   "BtoA_measured": 1.0526707104549757,
   "BtoA_constant": 0.9740450506112381,
   "BtoA_linear": 1.1925568783955782,
   "BtoA_quadratic": 0.9294241026110228,
   "BtoA_pure": 1.2784409108899695
  },
  {
   "catalog": "O4b",
   "event": "GW240825_055146",
   "axr_A": 4.732055203136397,
   "axr_B": 3.846369488501976,
   "AtoB_measured": 0.5346537204345623,
   "AtoB_constant": 1.151421758132443,
   "AtoB_linear": 0.9881380698684552,
   "AtoB_quadratic": 0.9597367966030106,
   "AtoB_pure": 1.3736526896554722,
   "BtoA_measured": 1.2594258877611537,
   "BtoA_constant": 1.5025135757169608,
   "BtoA_linear": 1.3276892450648745,
   "BtoA_quadratic": 1.107824218518516,
   "BtoA_pure": 1.6470420467327926
  },
  {
   "catalog": "O4b",
   "event": "GW240830_211120",
   "axr_A": 3.7002686677736243,
   "axr_B": 3.5281351731091575,
   "AtoB_measured": 2.4057765185124538,
   "AtoB_constant": 2.3416415531168013,
   "AtoB_linear": 1.7350530859665128,
   "AtoB_quadratic": 2.2666828109593666,
   "AtoB_pure": 2.670602161719472,
   "BtoA_measured": 3.252278712253485,
   "BtoA_constant": 2.868260238082968,
   "BtoA_linear": 2.8293812859781156,
   "BtoA_quadratic": 2.8019574396179223,
   "BtoA_pure": 3.0751225929031136
  },
  {
   "catalog": "O4b",
   "event": "GW240910_103535",
   "axr_A": 6.258949730149528,
   "axr_B": 5.632521451844568,
   "AtoB_measured": 0.6971028651939264,
   "AtoB_constant": 0.33819268431358296,
   "AtoB_linear": 0.6098240879137222,
   "AtoB_quadratic": 0.6100944645797597,
   "AtoB_pure": 0.47205162456256744,
   "BtoA_measured": 0.13814900665499863,
   "BtoA_constant": 0.07705720789397219,
   "BtoA_linear": 0.1553330555971968,
   "BtoA_quadratic": 0.06508891873846778,
   "BtoA_pure": 0.10304271140640253
  },
  {
   "catalog": "O4b",
   "event": "GW240915_001357",
   "axr_A": 7.16406175178025,
   "axr_B": 5.011013806648295,
   "AtoB_measured": 0.24264276400759854,
   "AtoB_constant": 0.30572251248017324,
   "AtoB_linear": 0.7016293441097332,
   "AtoB_quadratic": 0.2066861129578399,
   "AtoB_pure": 0.013798278508886597,
   "BtoA_measured": 0.18751275574589954,
   "BtoA_constant": 0.026618732844241322,
   "BtoA_linear": 0.31494213219215794,
   "BtoA_quadratic": 0.12284542629788575,
   "BtoA_pure": 0.28304818526558506
  },
  {
   "catalog": "O4b",
   "event": "GW240915_105151",
   "axr_A": 7.337572493908961,
   "axr_B": 5.507073085713072,
   "AtoB_measured": 0.9439563796705386,
   "AtoB_constant": 0.8359893055502425,
   "AtoB_linear": 1.2278108040613631,
   "AtoB_quadratic": 1.2492160584354792,
   "AtoB_pure": 0.8696860592528992,
   "BtoA_measured": 0.8976917275341805,
   "BtoA_constant": 1.1310442857695762,
   "BtoA_linear": 0.722478999322334,
   "BtoA_quadratic": 0.977803775575893,
   "BtoA_pure": 0.8555070051173459
  },
  {
   "catalog": "O4b",
   "event": "GW240920_073424",
   "axr_A": 3.6377440001282877,
   "axr_B": 3.580759913697068,
   "AtoB_measured": 1.0139361462811394,
   "AtoB_constant": 0.7861340319606427,
   "AtoB_linear": 0.8563200847626717,
   "AtoB_quadratic": 0.983815628225841,
   "AtoB_pure": 1.1375515776368843,
   "BtoA_measured": 1.8071018819987046,
   "BtoA_constant": 1.9413653014436534,
   "BtoA_linear": 1.4841204353652415,
   "BtoA_quadratic": 1.8478799621694293,
   "BtoA_pure": 2.0535873546292294
  },
  {
   "catalog": "O4b",
   "event": "GW240921_201835",
   "axr_A": 6.590705285486146,
   "axr_B": 5.630440385214587,
   "AtoB_measured": 2.33068228376672,
   "AtoB_constant": 2.5454544676643422,
   "AtoB_linear": 2.3976036899240114,
   "AtoB_quadratic": 2.2141617010888694,
   "AtoB_pure": 2.3715949893808386,
   "BtoA_measured": 1.5733989863910836,
   "BtoA_constant": 1.4289683852985604,
   "BtoA_linear": 1.337031828848751,
   "BtoA_quadratic": 1.3370019828197712,
   "BtoA_pure": 1.507127497758205
  },
  {
   "catalog": "O4b",
   "event": "GW240922_142106",
   "axr_A": 4.2775650215988525,
   "axr_B": 3.7879650099899185,
   "AtoB_measured": 0.9826313116076619,
   "AtoB_constant": 0.8502074242957178,
   "AtoB_linear": 1.0294160432588342,
   "AtoB_quadratic": 1.1080453317775607,
   "AtoB_pure": 1.3864056318832638,
   "BtoA_measured": 1.0732648552499882,
   "BtoA_constant": 1.3809888997103599,
   "BtoA_linear": 1.455897047487582,
   "BtoA_quadratic": 1.7231464262199836,
   "BtoA_pure": 1.701251367753997
  },
  {
   "catalog": "O4b",
   "event": "GW240930_035959",
   "axr_A": 4.550306835444252,
   "axr_B": 4.304732394497918,
   "AtoB_measured": 2.9646704640122152,
   "AtoB_constant": 2.5616363772432464,
   "AtoB_linear": 2.8868196606731544,
   "AtoB_quadratic": 2.9310896916168474,
   "AtoB_pure": 2.894978799889543,
   "BtoA_measured": 2.1232204773171475,
   "BtoA_constant": 2.366795044624098,
   "BtoA_linear": 1.9457440636720378,
   "BtoA_quadratic": 2.179160639843616,
   "BtoA_pure": 2.077161187435138
  },
  {
   "catalog": "O4b",
   "event": "GW241009_084816",
   "axr_A": 3.6066263031414127,
   "axr_B": 3.044584818902337,
   "AtoB_measured": 0.1284053593063561,
   "AtoB_constant": 0.5377798517228598,
   "AtoB_linear": 0.5872294052782934,
   "AtoB_quadratic": 0.3312358833143776,
   "AtoB_pure": 0.7722499171197228,
   "BtoA_measured": 0.218575712617195,
   "BtoA_constant": 0.12728148378383253,
   "BtoA_linear": 0.019766677115285347,
   "BtoA_quadratic": 0.060459409271061304,
   "BtoA_pure": 0.38505783070360167
  },
  {
   "catalog": "O4b",
   "event": "GW241011_233834",
   "axr_A": 22.01910633119258,
   "axr_B": 29.343802710967605,
   "AtoB_measured": 0.08488268357473316,
   "AtoB_constant": 0.07522882414721721,
   "AtoB_linear": 0.08246213408725112,
   "AtoB_quadratic": 0.06611257782154212,
   "AtoB_pure": 0.07561112228387401,
   "BtoA_measured": 0.5098978129323655,
   "BtoA_constant": 0.4879814710419055,
   "BtoA_linear": 0.5084635685763033,
   "BtoA_quadratic": 0.4966939695665644,
   "BtoA_pure": 0.46896704487735974
  },
  {
   "catalog": "O4b",
   "event": "GW241102_124058",
   "axr_A": 9.12186860082629,
   "axr_B": 8.247920566358433,
   "AtoB_measured": 0.47047380638250047,
   "AtoB_constant": 0.6042468040791675,
   "AtoB_linear": 0.5359463522630108,
   "AtoB_quadratic": 0.5567956068055651,
   "AtoB_pure": 0.5658519012116869,
   "BtoA_measured": 0.2949287464907684,
   "BtoA_constant": 0.5216255336377742,
   "BtoA_linear": 0.2670869607446207,
   "BtoA_quadratic": 0.3342865805621784,
   "BtoA_pure": 0.32464105082411265
  },
  {
   "catalog": "O4b",
   "event": "GW241109_115924",
   "axr_A": 5.348168165210446,
   "axr_B": 4.835091365959454,
   "AtoB_measured": 0.8800931308249744,
   "AtoB_constant": 1.0874232999445894,
   "AtoB_linear": 0.7575151196722629,
   "AtoB_quadratic": 0.6390597311981878,
   "AtoB_pure": 0.9057499151354307,
   "BtoA_measured": 0.7154323070292037,
   "BtoA_constant": 1.2545091984938495,
   "BtoA_linear": 0.8496175928954699,
   "BtoA_quadratic": 1.1815555509125488,
   "BtoA_pure": 1.081660690752102
  },
  {
   "catalog": "O4b",
   "event": "GW241110_124123",
   "axr_A": 6.730992855133639,
   "axr_B": 6.219320034522616,
   "AtoB_measured": 1.3367458509235348,
   "AtoB_constant": 1.2661597759291396,
   "AtoB_linear": 1.1399421703211488,
   "AtoB_quadratic": 1.2559514921098582,
   "AtoB_pure": 1.3992297173603845,
   "BtoA_measured": 1.4342633743958402,
   "BtoA_constant": 1.3951884167006199,
   "BtoA_linear": 1.4418646094985945,
   "BtoA_quadratic": 1.4702165683410442,
   "BtoA_pure": 1.4177826658021502
  },
  {
   "catalog": "O4b",
   "event": "GW241114_235258",
   "axr_A": 5.369355645279544,
   "axr_B": 3.6679637352522994,
   "AtoB_measured": 0.3804885646791547,
   "AtoB_constant": 0.3828273231723074,
   "AtoB_linear": 0.23800741265830538,
   "AtoB_quadratic": 0.519235261067621,
   "AtoB_pure": 0.5927028345759027,
   "BtoA_measured": 0.08506460322078624,
   "BtoA_constant": 0.3902180239337838,
   "BtoA_linear": 0.07830530975860484,
   "BtoA_quadratic": 0.1198371857076097,
   "BtoA_pure": 0.1285575050433465
  },
  {
   "catalog": "O4b",
   "event": "GW241130_110422",
   "axr_A": 4.831183585542378,
   "axr_B": 3.7898159110969143,
   "AtoB_measured": 1.468290853269366,
   "AtoB_constant": 1.562392811334007,
   "AtoB_linear": 1.609355302034544,
   "AtoB_quadratic": 1.4028927501981059,
   "AtoB_pure": 1.6386408440564821,
   "BtoA_measured": 0.9224161122288876,
   "BtoA_constant": 0.6585438253735845,
   "BtoA_linear": 0.7818915656733623,
   "BtoA_quadratic": 0.3970437248646874,
   "BtoA_pure": 1.0467277091382812
  },
  {
   "catalog": "O4b",
   "event": "GW241225_042553",
   "axr_A": 5.566952276121513,
   "axr_B": 4.890907763607683,
   "AtoB_measured": 2.180623377314788,
   "AtoB_constant": 2.323464682647767,
   "AtoB_linear": 2.012776687266438,
   "AtoB_quadratic": 2.1168751310989933,
   "AtoB_pure": 2.2790430502174672,
   "BtoA_measured": 1.268789017939099,
   "BtoA_constant": 1.406321034987485,
   "BtoA_linear": 1.1461277765629063,
   "BtoA_quadratic": 1.6109471329777136,
   "BtoA_pure": 1.4682547840284315
  },
  {
   "catalog": "O4b",
   "event": "GW241231_054133",
   "axr_A": 6.378416897942903,
   "axr_B": 5.577859164231567,
   "AtoB_measured": 0.9989360853933533,
   "AtoB_constant": 0.888787963462363,
   "AtoB_linear": 1.088252273038762,
   "AtoB_quadratic": 1.0790849964185156,
   "AtoB_pure": 0.8653853390144093,
   "BtoA_measured": 0.37351506158225334,
   "BtoA_constant": 0.32652461025065804,
   "BtoA_linear": 0.2827287731201409,
   "BtoA_quadratic": 0.28708435800081133,
   "BtoA_pure": 0.290891033746675
  },
  {
   "catalog": "O4b",
   "event": "GW250118_055802",
   "axr_A": 5.6095042058130415,
   "axr_B": 3.79054256930562,
   "AtoB_measured": 0.440132712101331,
   "AtoB_constant": 0.4133177117263074,
   "AtoB_linear": 1.2892007049827612,
   "AtoB_quadratic": 0.8848030567556862,
   "AtoB_pure": 1.303752266281947,
   "BtoA_measured": 0.4605611659686417,
   "BtoA_constant": 0.8045354506528213,
   "BtoA_linear": 0.6207473899575291,
   "BtoA_quadratic": 0.6285244844951308,
   "BtoA_pure": 0.9539816697077868
  },
  {
   "catalog": "O4b",
   "event": "GW250119_190238",
   "axr_A": 3.6942938360651145,
   "axr_B": 3.2766849127835993,
   "AtoB_measured": 2.3843730087489803,
   "AtoB_constant": 2.729515310225622,
   "AtoB_linear": 2.8544391290567432,
   "AtoB_quadratic": 2.8435210024097444,
   "AtoB_pure": 2.32575966618208,
   "BtoA_measured": 2.494567114265408,
   "BtoA_constant": 2.801575708796804,
   "BtoA_linear": 3.2280878442470566,
   "BtoA_quadratic": 2.926030655486585,
   "BtoA_pure": 2.7285293999397595
  }
 ]
}